Workbook

Sheet Avancement
A1: Avancement au 02/10/2026 — rapprochement rapports équipe ↔ product backlog
A2: Sources : Rapport d'activité technique Front mobile (Youssef Feki) · Référentiel d'avancement Jira OPT-101→302 (Ahmed Jmal, commits 194e90e, 8b71bae, 8b300db, 7dd0667). « En cours » compté à 50 % dans le % pondéré (hypothèse).
A4: Par développeur
B5: J/H total | C5: J/H Done | D5: J/H en cours | E5: J/H à faire | F5: Sous-tâches Done | G5: Sous-tâches en cours | H5: % Done (J/H) | I5: % pondéré
A6: Front | B6: =SUMIFS(Backlog!$K:$K,Backlog!$I:$I,$A6,Backlog!$B:$B,"Sous-tâche") -> 102.5 | C6: =SUMIFS(Backlog!$K:$K,Backlog!$I:$I,$A6,Backlog!$B:$B,"Sous-tâche",Backlog!$Q:$Q,"Done") -> 5 | D6: =SUMIFS(Backlog!$K:$K,Backlog!$I:$I,$A6,Backlog!$B:$B,"Sous-tâche",Backlog!$Q:$Q,"In Progress") -> 2 | E6: =B6-C6-D6 -> 95.5 | F6: =COUNTIFS(Backlog!$I:$I,$A6,Backlog!$B:$B,"Sous-tâche",Backlog!$Q:$Q,"Done") -> 4 | G6: =COUNTIFS(Backlog!$I:$I,$A6,Backlog!$B:$B,"Sous-tâche",Backlog!$Q:$Q,"In Progress") -> 3 | H6: =IF(B6=0,0,C6/B6) -> 0.048780488 | I6: =IF(B6=0,0,(C6+0.5*D6)/B6) -> 0.058536585 | J6: Youssef Feki
A7: Back | B7: =SUMIFS(Backlog!$K:$K,Backlog!$I:$I,$A7,Backlog!$B:$B,"Sous-tâche") -> 125 | C7: =SUMIFS(Backlog!$K:$K,Backlog!$I:$I,$A7,Backlog!$B:$B,"Sous-tâche",Backlog!$Q:$Q,"Done") -> 19.5 | D7: =SUMIFS(Backlog!$K:$K,Backlog!$I:$I,$A7,Backlog!$B:$B,"Sous-tâche",Backlog!$Q:$Q,"In Progress") -> 12 | E7: =B7-C7-D7 -> 93.5 | F7: =COUNTIFS(Backlog!$I:$I,$A7,Backlog!$B:$B,"Sous-tâche",Backlog!$Q:$Q,"Done") -> 17 | G7: =COUNTIFS(Backlog!$I:$I,$A7,Backlog!$B:$B,"Sous-tâche",Backlog!$Q:$Q,"In Progress") -> 8 | H7: =IF(B7=0,0,C7/B7) -> 0.156 | I7: =IF(B7=0,0,(C7+0.5*D7)/B7) -> 0.204 | J7: Ahmed Jmal (Back + BDD)
A8: IA | B8: =SUMIFS(Backlog!$K:$K,Backlog!$I:$I,$A8,Backlog!$B:$B,"Sous-tâche") -> 40 | C8: =SUMIFS(Backlog!$K:$K,Backlog!$I:$I,$A8,Backlog!$B:$B,"Sous-tâche",Backlog!$Q:$Q,"Done") -> 0 | D8: =SUMIFS(Backlog!$K:$K,Backlog!$I:$I,$A8,Backlog!$B:$B,"Sous-tâche",Backlog!$Q:$Q,"In Progress") -> 0 | E8: =B8-C8-D8 -> 40 | F8: =COUNTIFS(Backlog!$I:$I,$A8,Backlog!$B:$B,"Sous-tâche",Backlog!$Q:$Q,"Done") -> 0 | G8: =COUNTIFS(Backlog!$I:$I,$A8,Backlog!$B:$B,"Sous-tâche",Backlog!$Q:$Q,"In Progress") -> 0 | H8: =IF(B8=0,0,C8/B8) -> 0 | I8: =IF(B8=0,0,(C8+0.5*D8)/B8) -> 0 | J8: Yessine Affes
A9: DevOps | B9: =SUMIFS(Backlog!$K:$K,Backlog!$I:$I,$A9,Backlog!$B:$B,"Sous-tâche") -> 42 | C9: =SUMIFS(Backlog!$K:$K,Backlog!$I:$I,$A9,Backlog!$B:$B,"Sous-tâche",Backlog!$Q:$Q,"Done") -> 0 | D9: =SUMIFS(Backlog!$K:$K,Backlog!$I:$I,$A9,Backlog!$B:$B,"Sous-tâche",Backlog!$Q:$Q,"In Progress") -> 4 | E9: =B9-C9-D9 -> 38 | F9: =COUNTIFS(Backlog!$I:$I,$A9,Backlog!$B:$B,"Sous-tâche",Backlog!$Q:$Q,"Done") -> 0 | G9: =COUNTIFS(Backlog!$I:$I,$A9,Backlog!$B:$B,"Sous-tâche",Backlog!$Q:$Q,"In Progress") -> 2 | H9: =IF(B9=0,0,C9/B9) -> 0 | I9: =IF(B9=0,0,(C9+0.5*D9)/B9) -> 0.047619048 | J9: Heni Kenoun
A11: Par sprint (sprints concernés)
B12: J/H total | C12: J/H Done | D12: J/H en cours | E12: J/H à faire | F12: Sous-tâches Done | G12: Sous-tâches en cours | H12: % Done (J/H) | I12: % pondéré
A13: S01 | B13: =SUMIFS(Backlog!$K:$K,Backlog!$N:$N,$A13,Backlog!$B:$B,"Sous-tâche") -> 25.5 | C13: =SUMIFS(Backlog!$K:$K,Backlog!$N:$N,$A13,Backlog!$B:$B,"Sous-tâche",Backlog!$Q:$Q,"Done") -> 9 | D13: =SUMIFS(Backlog!$K:$K,Backlog!$N:$N,$A13,Backlog!$B:$B,"Sous-tâche",Backlog!$Q:$Q,"In Progress") -> 10.5 | E13: =B13-C13-D13 -> 6 | F13: =COUNTIFS(Backlog!$N:$N,$A13,Backlog!$B:$B,"Sous-tâche",Backlog!$Q:$Q,"Done") -> 9 | G13: =COUNTIFS(Backlog!$N:$N,$A13,Backlog!$B:$B,"Sous-tâche",Backlog!$Q:$Q,"In Progress") -> 8 | H13: =IF(B13=0,0,C13/B13) -> 0.35294118 | I13: =IF(B13=0,0,(C13+0.5*D13)/B13) -> 0.55882353
A14: S02 | B14: =SUMIFS(Backlog!$K:$K,Backlog!$N:$N,$A14,Backlog!$B:$B,"Sous-tâche") -> 26.5 | C14: =SUMIFS(Backlog!$K:$K,Backlog!$N:$N,$A14,Backlog!$B:$B,"Sous-tâche",Backlog!$Q:$Q,"Done") -> 6.5 | D14: =SUMIFS(Backlog!$K:$K,Backlog!$N:$N,$A14,Backlog!$B:$B,"Sous-tâche",Backlog!$Q:$Q,"In Progress") -> 5.5 | E14: =B14-C14-D14 -> 14.5 | F14: =COUNTIFS(Backlog!$N:$N,$A14,Backlog!$B:$B,"Sous-tâche",Backlog!$Q:$Q,"Done") -> 5 | G14: =COUNTIFS(Backlog!$N:$N,$A14,Backlog!$B:$B,"Sous-tâche",Backlog!$Q:$Q,"In Progress") -> 3 | H14: =IF(B14=0,0,C14/B14) -> 0.24528302 | I14: =IF(B14=0,0,(C14+0.5*D14)/B14) -> 0.3490566
A15: S03 | B15: =SUMIFS(Backlog!$K:$K,Backlog!$N:$N,$A15,Backlog!$B:$B,"Sous-tâche") -> 30 | C15: =SUMIFS(Backlog!$K:$K,Backlog!$N:$N,$A15,Backlog!$B:$B,"Sous-tâche",Backlog!$Q:$Q,"Done") -> 5.5 | D15: =SUMIFS(Backlog!$K:$K,Backlog!$N:$N,$A15,Backlog!$B:$B,"Sous-tâche",Backlog!$Q:$Q,"In Progress") -> 0 | E15: =B15-C15-D15 -> 24.5 | F15: =COUNTIFS(Backlog!$N:$N,$A15,Backlog!$B:$B,"Sous-tâche",Backlog!$Q:$Q,"Done") -> 4 | G15: =COUNTIFS(Backlog!$N:$N,$A15,Backlog!$B:$B,"Sous-tâche",Backlog!$Q:$Q,"In Progress") -> 0 | H15: =IF(B15=0,0,C15/B15) -> 0.18333333 | I15: =IF(B15=0,0,(C15+0.5*D15)/B15) -> 0.18333333
A16: S04 | B16: =SUMIFS(Backlog!$K:$K,Backlog!$N:$N,$A16,Backlog!$B:$B,"Sous-tâche") -> 21.5 | C16: =SUMIFS(Backlog!$K:$K,Backlog!$N:$N,$A16,Backlog!$B:$B,"Sous-tâche",Backlog!$Q:$Q,"Done") -> 0 | D16: =SUMIFS(Backlog!$K:$K,Backlog!$N:$N,$A16,Backlog!$B:$B,"Sous-tâche",Backlog!$Q:$Q,"In Progress") -> 0 | E16: =B16-C16-D16 -> 21.5 | F16: =COUNTIFS(Backlog!$N:$N,$A16,Backlog!$B:$B,"Sous-tâche",Backlog!$Q:$Q,"Done") -> 0 | G16: =COUNTIFS(Backlog!$N:$N,$A16,Backlog!$B:$B,"Sous-tâche",Backlog!$Q:$Q,"In Progress") -> 0 | H16: =IF(B16=0,0,C16/B16) -> 0 | I16: =IF(B16=0,0,(C16+0.5*D16)/B16) -> 0
A17: S05 | B17: =SUMIFS(Backlog!$K:$K,Backlog!$N:$N,$A17,Backlog!$B:$B,"Sous-tâche") -> 22 | C17: =SUMIFS(Backlog!$K:$K,Backlog!$N:$N,$A17,Backlog!$B:$B,"Sous-tâche",Backlog!$Q:$Q,"Done") -> 1 | D17: =SUMIFS(Backlog!$K:$K,Backlog!$N:$N,$A17,Backlog!$B:$B,"Sous-tâche",Backlog!$Q:$Q,"In Progress") -> 2 | E17: =B17-C17-D17 -> 19 | F17: =COUNTIFS(Backlog!$N:$N,$A17,Backlog!$B:$B,"Sous-tâche",Backlog!$Q:$Q,"Done") -> 1 | G17: =COUNTIFS(Backlog!$N:$N,$A17,Backlog!$B:$B,"Sous-tâche",Backlog!$Q:$Q,"In Progress") -> 2 | H17: =IF(B17=0,0,C17/B17) -> 0.045454545 | I17: =IF(B17=0,0,(C17+0.5*D17)/B17) -> 0.090909091
A18: S07 | B18: =SUMIFS(Backlog!$K:$K,Backlog!$N:$N,$A18,Backlog!$B:$B,"Sous-tâche") -> 26.5 | C18: =SUMIFS(Backlog!$K:$K,Backlog!$N:$N,$A18,Backlog!$B:$B,"Sous-tâche",Backlog!$Q:$Q,"Done") -> 1 | D18: =SUMIFS(Backlog!$K:$K,Backlog!$N:$N,$A18,Backlog!$B:$B,"Sous-tâche",Backlog!$Q:$Q,"In Progress") -> 0 | E18: =B18-C18-D18 -> 25.5 | F18: =COUNTIFS(Backlog!$N:$N,$A18,Backlog!$B:$B,"Sous-tâche",Backlog!$Q:$Q,"Done") -> 1 | G18: =COUNTIFS(Backlog!$N:$N,$A18,Backlog!$B:$B,"Sous-tâche",Backlog!$Q:$Q,"In Progress") -> 0 | H18: =IF(B18=0,0,C18/B18) -> 0.037735849 | I18: =IF(B18=0,0,(C18+0.5*D18)/B18) -> 0.037735849
A19: S11 | B19: =SUMIFS(Backlog!$K:$K,Backlog!$N:$N,$A19,Backlog!$B:$B,"Sous-tâche") -> 39 | C19: =SUMIFS(Backlog!$K:$K,Backlog!$N:$N,$A19,Backlog!$B:$B,"Sous-tâche",Backlog!$Q:$Q,"Done") -> 1.5 | D19: =SUMIFS(Backlog!$K:$K,Backlog!$N:$N,$A19,Backlog!$B:$B,"Sous-tâche",Backlog!$Q:$Q,"In Progress") -> 0 | E19: =B19-C19-D19 -> 37.5 | F19: =COUNTIFS(Backlog!$N:$N,$A19,Backlog!$B:$B,"Sous-tâche",Backlog!$Q:$Q,"Done") -> 1 | G19: =COUNTIFS(Backlog!$N:$N,$A19,Backlog!$B:$B,"Sous-tâche",Backlog!$Q:$Q,"In Progress") -> 0 | H19: =IF(B19=0,0,C19/B19) -> 0.038461538 | I19: =IF(B19=0,0,(C19+0.5*D19)/B19) -> 0.038461538
A21: Par lot
B22: J/H total | C22: J/H Done | D22: J/H en cours | E22: J/H à faire | F22: Sous-tâches Done | G22: Sous-tâches en cours | H22: % Done (J/H) | I22: % pondéré
A23: Lot 1 | B23: =SUMIFS(Backlog!$K:$K,Backlog!$C:$C,$A23,Backlog!$B:$B,"Sous-tâche") -> 188 | C23: =SUMIFS(Backlog!$K:$K,Backlog!$C:$C,$A23,Backlog!$B:$B,"Sous-tâche",Backlog!$Q:$Q,"Done") -> 23 | D23: =SUMIFS(Backlog!$K:$K,Backlog!$C:$C,$A23,Backlog!$B:$B,"Sous-tâche",Backlog!$Q:$Q,"In Progress") -> 18 | E23: =B23-C23-D23 -> 147 | F23: =COUNTIFS(Backlog!$C:$C,$A23,Backlog!$B:$B,"Sous-tâche",Backlog!$Q:$Q,"Done") -> 20 | G23: =COUNTIFS(Backlog!$C:$C,$A23,Backlog!$B:$B,"Sous-tâche",Backlog!$Q:$Q,"In Progress") -> 13 | H23: =IF(B23=0,0,C23/B23) -> 0.12234043 | I23: =IF(B23=0,0,(C23+0.5*D23)/B23) -> 0.17021277
A24: Lot 2 | B24: =SUMIFS(Backlog!$K:$K,Backlog!$C:$C,$A24,Backlog!$B:$B,"Sous-tâche") -> 31 | C24: =SUMIFS(Backlog!$K:$K,Backlog!$C:$C,$A24,Backlog!$B:$B,"Sous-tâche",Backlog!$Q:$Q,"Done") -> 0 | D24: =SUMIFS(Backlog!$K:$K,Backlog!$C:$C,$A24,Backlog!$B:$B,"Sous-tâche",Backlog!$Q:$Q,"In Progress") -> 0 | E24: =B24-C24-D24 -> 31 | F24: =COUNTIFS(Backlog!$C:$C,$A24,Backlog!$B:$B,"Sous-tâche",Backlog!$Q:$Q,"Done") -> 0 | G24: =COUNTIFS(Backlog!$C:$C,$A24,Backlog!$B:$B,"Sous-tâche",Backlog!$Q:$Q,"In Progress") -> 0 | H24: =IF(B24=0,0,C24/B24) -> 0 | I24: =IF(B24=0,0,(C24+0.5*D24)/B24) -> 0
A25: Lot 3 | B25: =SUMIFS(Backlog!$K:$K,Backlog!$C:$C,$A25,Backlog!$B:$B,"Sous-tâche") -> 90.5 | C25: =SUMIFS(Backlog!$K:$K,Backlog!$C:$C,$A25,Backlog!$B:$B,"Sous-tâche",Backlog!$Q:$Q,"Done") -> 1.5 | D25: =SUMIFS(Backlog!$K:$K,Backlog!$C:$C,$A25,Backlog!$B:$B,"Sous-tâche",Backlog!$Q:$Q,"In Progress") -> 0 | E25: =B25-C25-D25 -> 89 | F25: =COUNTIFS(Backlog!$C:$C,$A25,Backlog!$B:$B,"Sous-tâche",Backlog!$Q:$Q,"Done") -> 1 | G25: =COUNTIFS(Backlog!$C:$C,$A25,Backlog!$B:$B,"Sous-tâche",Backlog!$Q:$Q,"In Progress") -> 0 | H25: =IF(B25=0,0,C25/B25) -> 0.016574586 | I25: =IF(B25=0,0,(C25+0.5*D25)/B25) -> 0.016574586
A27: Lecture
A28: • Le Back a déjà livré le cœur du module vendeurs (prévu S02-S03) et l'authentification (S01) avant la date de début planifiée (05/10) : avance sur le Back, qui est le goulot du projet.
A29: • Le Front a terminé l'essentiel de S01 (socle mobile, connexion, mot de passe oublié) ; les écrans vendeurs (US-52/53/54/55) restent à faire et dépendent d'API déjà prêtes.
A30: • Aucun livrable DevOps (Heni Kenoun) ni IA (Yessine Affes) dans les rapports : US-10 environnements Recette / Prod et US-11 CI/CD ne sont pas commencés par le DevOps.
A31: • Les 5 tâches réalisées hors backlog (≈ 4,5 J/H) ont été ajoutées à la fin de l'onglet Backlog (statut Done, source « À valider »).

Sheet Rapprochement OPT
A1: Correspondance tickets de l'équipe ↔ clés du product backlog
A3: Réf. équipe | B3: Titre (rapport équipe) | C3: SP équipe | D3: Développeur | E3: Commit | F3: Clés backlog couvertes | G3: Verdict | H3: Commentaire
A4: OPT-101 | B4: Infrastructure Docker, base de données & rôles PostgreSQL 17 | C4: 3 | D4: Ahmed Jmal | E4: 194e90e | F4: US-01-T3, US-04-T3, US-06-T1, US-05-T1 (partiel), US-10-T2 (partiel), US-40-T3 | G4: Conforme + avance | H4: Travail d'infra de dev fait par le Back ; les environnements Recette / Prod restent au DevOps.
A5: OPT-102 | B5: Authentification stateless JWT & Argon2id | C5: 5 | D5: Ahmed Jmal | E5: 194e90e | F5: US-01-T1 | G5: Conforme
A6: OPT-103 | B6: Découplage tokens / données utilisateur (/auth/me) | C6: 3 | D6: Ahmed Jmal | E6: 8b300db | F6: US-01 (nouvelle sous-tâche), US-03-T2 (partiel) | G6: Hors backlog | H6: Ajouté sous US-01.
A7: OPT-104 | B7: Réinitialisation de mot de passe en 3 étapes | C7: 5 | D7: Ahmed Jmal | E7: 8b71bae | F7: US-02-T1 | G7: Écart à valider | H7: OTP par e-mail au lieu d'un lien ; politique mot de passe 6-128 car. (faible).
A8: OPT-105 | B8: Double rate limiting & anti-énumération | C8: 3 | D8: Ahmed Jmal | E8: 194e90e | F8: US-09-T3 | G8: Écart à valider | H8: Pas de temporisation du compte après 5 échecs (critère backlog).
A9: OPT-201 | B9: Cycle de vie des statuts vendeurs | C9: 3 | D9: Ahmed Jmal | E9: 7dd0667 | F9: US-52-T1, US-52-T2 | G9: Conforme
A10: OPT-202 | B10: Affectations multi-sites & historisation | C10: 5 | D10: Ahmed Jmal | E10: 7dd0667 | F10: US-53-T1 + nouvelle sous-tâche US-53 | G10: Conforme + plus | H10: Historique daté non prévu au backlog.
A11: OPT-203 | B11: Planning ISO 7 jours & fuseaux IANA | C11: 5 | D11: Ahmed Jmal | E11: 7dd0667 | F11: US-54-T1, US-54-T2 | G11: Conforme | H11: Tranche la question ouverte : planning par affectation vendeur ↔ site.
A12: OPT-204 | B12: Contrôle d'accès dynamique temps réel | C12: 5 | D12: Ahmed Jmal | E12: 7dd0667 | F12: US-54-T1, US-52-T2, US-09-T1 (partiel) | G12: Conforme
A13: OPT-205 | B13: Onboarding vendeur : mot de passe temporaire & premier login | C13: 5 | D13: Ahmed Jmal | E13: 7dd0667 | F13: US-52 (nouvelle sous-tâche) | G13: Hors backlog | H13: Ajouté sous US-52.
A14: OPT-206 | B14: Activation PENDING / ACTIVATED & renvoi d'invitation | C14: 3 | D14: Ahmed Jmal | E14: 7dd0667 | F14: US-52 (nouvelle sous-tâche) | G14: Hors backlog | H14: Regroupé avec OPT-205.
A15: OPT-207 | B15: API REST de gestion des vendeurs | C15: 3 | D15: Ahmed Jmal | E15: 7dd0667 | F15: US-52-T1, US-03-T2 (partiel) | G15: Conforme
A16: OPT-301 | B16: Codes d'erreurs métier & exceptions HTTP | C16: 2 | D16: Ahmed Jmal | E16: 194e90e | F16: US-08 (nouvelle sous-tâche), US-08-T3 (partiel) | G16: Hors backlog | H16: Ajouté sous US-08.
A17: OPT-302 | B17: Tests E2E et unitaires, mocks SMTP | C17: 2 | D17: Ahmed Jmal | E17: 7dd0667 | F17: US-02-T3, US-55-T2 | G17: Conforme | H17: Tests SIVO / Oracle (US-07) non couverts.
A18: Front §3A | B18: Initialisation & configuration de l'app mobile | D18: Youssef Feki | E18: feature/login | F18: US-59-T1, US-59-T2 (partiel) | G18: Conforme | H18: React Native retenu (question ouverte tranchée).
A19: Front §3B-C | B19: Connexion sécurisée & gestion de session JWT | D19: Youssef Feki | E19: feature/login | F19: US-01-T2, US-09-T4 (partiel) | G19: Conforme | H19: Certificate pinning à prévoir.
A20: Front §3D | B20: Réinitialisation de mot de passe OTP | D20: Youssef Feki | E20: feature/login | F20: US-02-T2 | G20: Conforme
A21: Front §3E | B21: Navigation & écran d'accueil / profil | D21: Youssef Feki | E21: feature/login | F21: US-01 (nouvelle sous-tâche), US-03-T3 (partiel) | G21: Hors backlog | H21: Ajouté sous US-01.
A22: Front §4 | B22: Tests automatisés (8 suites, 36 tests) | D22: Youssef Feki | E22: feature/login | F22: Definition of Done | G22: Conforme

Sheet Écarts à arbitrer
A1: Écarts entre le réalisé et le backlog — décision PO requise
A3: # | B3: Écart constaté | C3: Clé backlog | D3: Recommandation PO | E3: Décision
A4: 1 | B4: Base de données applicative PostgreSQL 17 (NestJS / Prisma) alors que le CDC parle du système de production Oracle SIVO. | C4: US-04, US-05 | D4: OK si PostgreSQL = base de l'application et Oracle = système SIVO intégré par API / connecteur. À confirmer par écrit avec l'IT SIVO avant S02.
A5: 2 | B5: Mot de passe oublié par code OTP e-mail (et non lien valable 30 min). | C5: US-02 | D5: Accepter (plus adapté au mobile) et mettre à jour le critère d'acceptation.
A6: 3 | B6: Politique de mot de passe 6 à 128 caractères. | C6: US-02, US-52 | D6: Trop faible pour une application B2B : passer à 12 caractères minimum ou s'aligner sur la politique SIVO.
A7: 4 | B7: Pas de temporisation du compte après 5 échecs ; protection par rate limiting. | C7: US-09-T3 | D7: Accepter le rate limiting et ajouter un verrouillage progressif par compte, ou modifier le critère.
A8: 5 | B8: Pas de table sessions (architecture stateless) ; révocation par revérification du profil. | C8: US-01-T3, US-52-T2 | D8: Accepter : le critère « session révocable » est couvert par le contrôle à chaque requête.
A9: 6 | B9: Plages horaires définies par affectation vendeur ↔ site (et non par vendeur). | C9: US-54 | D9: Accepter : tranche la question ouverte n° 7 ; mettre à jour le critère.
A10: 7 | B10: Infra Docker de dev réalisée par le Back ; aucun livrable DevOps signalé. | C10: US-10, US-11 | D10: Confirmer avec Heni Kenoun le démarrage de US-10 (environnements) et US-11 (CI/CD), prérequis de la recette.
A11: 8 | B11: Tickets créés par l'équipe avec ses propres clés (OPT-xxx, 3 épics). | C11: Tous | D11: Ne pas créer les épics EPIC-1/2/3 : rattacher chaque OPT-xxx aux clés du backlog (voir l'onglet Rapprochement OPT) pour garder un seul référentiel.

Sheet Synthèse
A1: Plateforme Opticien ↔ ESSILOR SIVO — Backlog v2
A2: Sources : Cahier des charges v2.0 (sept. 2026, accepté par SIVO) · Devis NextStep 27082601-L1/L2/L3 du 27/08/2026 · Ajout module Vendeurs (Lot 1).
A4: Vision produit
A5: Nous aidons les opticiens clients d'ESSILOR SIVO à commander (Stock, RX, Précal), suivre, réclamer et gérer leurs équipes depuis le mobile puis le web, en remplaçant le fax et les outils hétérogènes par une plateforme unique intégrée au système Oracle — mesuré par le % de commandes et de précals passés en ligne, le taux d'erreurs de commande et la baisse des appels au support.
A7: Product Goals par lot (découpage CDC v2)
A8: Lot 1 | B8: Commandes Stock / RX / Précal digital, suivi notifié, réclamations, vendeurs avec accès par site et horaire — sur mobile, socle sécurisé intégré à Oracle.
A9: Lot 2 | B9: Favoris, tracking et décharge électronique, espace commercial du représentant.
A10: Lot 3 | B10: Recommandation et chatbot IA aux seuils de qualité / sécurité validés ; exploitation autonome par l'IT SIVO.
A11: Web | B11: Après le mobile : déclinaison web de chaque module sur le même backend (sans logique métier dupliquée).
A13: Charge par lot : couvert par le devis vs à valider
A14: Lot | B14: J/H couverts devis | C14: J/H à valider | D14: Total J/H | E14: % à valider | F14: Épics | G14: Stories | H14: Sous-tâches | I14: dont web (J/H)
A15: Lot 1 | B15: =SUMIFS(Backlog!$K:$K,Backlog!$C:$C,$A15,Backlog!$O:$O,"Devis",Backlog!$B:$B,"Sous-tâche") -> 97 | C15: =SUMIFS(Backlog!$K:$K,Backlog!$C:$C,$A15,Backlog!$O:$O,"À valider",Backlog!$B:$B,"Sous-tâche") -> 91 | D15: =B15+C15 -> 188 | E15: =IF(D15=0,0,C15/D15) -> 0.48404255 | F15: =COUNTIFS(Backlog!$C:$C,$A15,Backlog!$B:$B,"Epic") -> 11 | G15: =COUNTIFS(Backlog!$C:$C,$A15,Backlog!$B:$B,"Story") -> 44 | H15: =COUNTIFS(Backlog!$C:$C,$A15,Backlog!$B:$B,"Sous-tâche") -> 112 | I15: =SUMIFS(Backlog!$K:$K,Backlog!$C:$C,$A15,Backlog!$H:$H,"Front Web",Backlog!$B:$B,"Sous-tâche") -> 29
A16: Lot 2 | B16: =SUMIFS(Backlog!$K:$K,Backlog!$C:$C,$A16,Backlog!$O:$O,"Devis",Backlog!$B:$B,"Sous-tâche") -> 10 | C16: =SUMIFS(Backlog!$K:$K,Backlog!$C:$C,$A16,Backlog!$O:$O,"À valider",Backlog!$B:$B,"Sous-tâche") -> 21 | D16: =B16+C16 -> 31 | E16: =IF(D16=0,0,C16/D16) -> 0.67741935 | F16: =COUNTIFS(Backlog!$C:$C,$A16,Backlog!$B:$B,"Epic") -> 3 | G16: =COUNTIFS(Backlog!$C:$C,$A16,Backlog!$B:$B,"Story") -> 10 | H16: =COUNTIFS(Backlog!$C:$C,$A16,Backlog!$B:$B,"Sous-tâche") -> 25 | I16: =SUMIFS(Backlog!$K:$K,Backlog!$C:$C,$A16,Backlog!$H:$H,"Front Web",Backlog!$B:$B,"Sous-tâche") -> 6
A17: Lot 3 | B17: =SUMIFS(Backlog!$K:$K,Backlog!$C:$C,$A17,Backlog!$O:$O,"Devis",Backlog!$B:$B,"Sous-tâche") -> 83 | C17: =SUMIFS(Backlog!$K:$K,Backlog!$C:$C,$A17,Backlog!$O:$O,"À valider",Backlog!$B:$B,"Sous-tâche") -> 7.5 | D17: =B17+C17 -> 90.5 | E17: =IF(D17=0,0,C17/D17) -> 0.082872928 | F17: =COUNTIFS(Backlog!$C:$C,$A17,Backlog!$B:$B,"Epic") -> 6 | G17: =COUNTIFS(Backlog!$C:$C,$A17,Backlog!$B:$B,"Story") -> 20 | H17: =COUNTIFS(Backlog!$C:$C,$A17,Backlog!$B:$B,"Sous-tâche") -> 55 | I17: =SUMIFS(Backlog!$K:$K,Backlog!$C:$C,$A17,Backlog!$H:$H,"Front Web",Backlog!$B:$B,"Sous-tâche") -> 3.5
A18: TOTAL | B18: =SUM(B15:B17) -> 190 | C18: =SUM(C15:C17) -> 119.5 | D18: =SUM(D15:D17) -> 309.5 | E18: =IF(D18=0,0,C18/D18) -> 0.38610662 | F18: =SUM(F15:F17) -> 20 | G18: =SUM(G15:G17) -> 74 | H18: =SUM(H15:H17) -> 192 | I18: =SUM(I15:I17) -> 38.5
A19: Devis signé (réf.) | B19: 190 | C19: ="Contrôle : "&IF(B18=B19,"OK","écart "&TEXT(B18-B19,"0.0")) -> Contrôle : OK
A20: Les J/H « à valider » (module vendeurs, Précal digital, espace commercial, notifications, mobile, version web…) sont à chiffrer en avenant avec SIVO.
A22: Charge par personne et par lot (J/H)
A23: Personne | B23: Lot 1 | C23: Lot 2 | D23: Lot 3 | E23: Total | F23: Nb sous-tâches
A24: Front | B24: =SUMIFS(Backlog!$K:$K,Backlog!$C:$C,"Lot 1",Backlog!$I:$I,$A24,Backlog!$B:$B,"Sous-tâche") -> 76 | C24: =SUMIFS(Backlog!$K:$K,Backlog!$C:$C,"Lot 2",Backlog!$I:$I,$A24,Backlog!$B:$B,"Sous-tâche") -> 17 | D24: =SUMIFS(Backlog!$K:$K,Backlog!$C:$C,"Lot 3",Backlog!$I:$I,$A24,Backlog!$B:$B,"Sous-tâche") -> 9.5 | E24: =SUM(B24:D24) -> 102.5 | F24: =COUNTIFS(Backlog!$I:$I,$A24,Backlog!$B:$B,"Sous-tâche") -> 59
A25: Back | B25: =SUMIFS(Backlog!$K:$K,Backlog!$C:$C,"Lot 1",Backlog!$I:$I,$A25,Backlog!$B:$B,"Sous-tâche") -> 89.5 | C25: =SUMIFS(Backlog!$K:$K,Backlog!$C:$C,"Lot 2",Backlog!$I:$I,$A25,Backlog!$B:$B,"Sous-tâche") -> 14 | D25: =SUMIFS(Backlog!$K:$K,Backlog!$C:$C,"Lot 3",Backlog!$I:$I,$A25,Backlog!$B:$B,"Sous-tâche") -> 21.5 | E25: =SUM(B25:D25) -> 125 | F25: =COUNTIFS(Backlog!$I:$I,$A25,Backlog!$B:$B,"Sous-tâche") -> 90
A26: IA | B26: =SUMIFS(Backlog!$K:$K,Backlog!$C:$C,"Lot 1",Backlog!$I:$I,$A26,Backlog!$B:$B,"Sous-tâche") -> 0 | C26: =SUMIFS(Backlog!$K:$K,Backlog!$C:$C,"Lot 2",Backlog!$I:$I,$A26,Backlog!$B:$B,"Sous-tâche") -> 0 | D26: =SUMIFS(Backlog!$K:$K,Backlog!$C:$C,"Lot 3",Backlog!$I:$I,$A26,Backlog!$B:$B,"Sous-tâche") -> 40 | E26: =SUM(B26:D26) -> 40 | F26: =COUNTIFS(Backlog!$I:$I,$A26,Backlog!$B:$B,"Sous-tâche") -> 21
A27: DevOps | B27: =SUMIFS(Backlog!$K:$K,Backlog!$C:$C,"Lot 1",Backlog!$I:$I,$A27,Backlog!$B:$B,"Sous-tâche") -> 22.5 | C27: =SUMIFS(Backlog!$K:$K,Backlog!$C:$C,"Lot 2",Backlog!$I:$I,$A27,Backlog!$B:$B,"Sous-tâche") -> 0 | D27: =SUMIFS(Backlog!$K:$K,Backlog!$C:$C,"Lot 3",Backlog!$I:$I,$A27,Backlog!$B:$B,"Sous-tâche") -> 19.5 | E27: =SUM(B27:D27) -> 42 | F27: =COUNTIFS(Backlog!$I:$I,$A27,Backlog!$B:$B,"Sous-tâche") -> 22
A28: TOTAL | B28: =SUM(B24:B27) -> 188 | C28: =SUM(C24:C27) -> 31 | D28: =SUM(D24:D27) -> 90.5 | E28: =SUM(E24:E27) -> 309.5 | F28: =SUM(F24:F27) -> 192
A30: Risque planning & leviers
A31: Fin estimée | B31: =Sprints!O22 -> 46527
A32: Échéance CDC | B32: =Sprints!B7 -> 46444
A33: Statut | B33: =Sprints!D28 -> RETARD — voir leviers ci-dessous
A34: 1. Ajouter un 2e développeur Back ou confier une partie de la BDD à Heni Kenoun (DevOps) : le Back porte ~120 J/H seul, plus que les jours ouvrés jusqu'à fin février.
A35: 2. Livrer en février le Lot 1 mobile (S01–S07) et négocier Lots 2-3 + web en phase 2.
A36: 3. Réduire le périmètre web au strict nécessaire (back-offices SIVO déjà en web) et décaler le web opticien.
A37: 4. Passer le facteur de focus à 80 % dans l'onglet Sprints pour voir le planning réaliste.
A39: Hypothèses
A40: • Équipe : Youssef Feki (Front, mobile puis web), Ahmed Jmal (Back + BDD), Yessine Affes (IA), Heni Kenoun (DevOps).
A41: • Un seul backend / une seule API pour le mobile et le web.
A42: • Mobile d'abord (Lots 1 et 2 entièrement en mobile), puis web à partir de S09 en parallèle des sprints IA du Lot 3.
A43: • Les back-offices SIVO (réclamations, précal) sont en web dès le Lot 1 : ils servent aux équipes SIVO, pas aux opticiens.
A44: • Charge web ≈ 50 % du mobile (API et règles déjà faites) — à valider.
A45: • L'ancienne « détection IA des bons Précal » est retirée : le CDC v2 digitalise le bon (plus de papier à lire). L'aide à la saisie précal passe par le chatbot.

Sheet Sprints
A1: Plan de sprints — mobile d'abord, web ensuite — durée variable selon la capacité
A2: 1 personne par rôle : durée = charge de la personne la plus chargée (goulot) / facteur de focus + jours de cérémonies. Cellules jaunes modifiables.
A4: Date de début du projet | B4: 46300
A5: Jours de cérémonies / sprint (planning, review, rétro) | B5: 1
A6: Facteur de focus (capacité réelle / théorique) | B6: 1 | C6: Mettre 80 % pour intégrer imprévus / support.
A7: Échéance cahier des charges | B7: 46444 | C7: CDC v2 : « Échéance : février 2027 » (dernier jour ouvré retenu).
A9: Sprint | B9: Lot | C9: Nom | D9: Sprint Goal | E9: Front – Youssef Feki (J/H) | F9: dont Mobile | G9: dont Web | H9: Back+BDD – Ahmed Jmal (J/H) | I9: IA – Yessine Affes (J/H) | J9: DevOps – Heni Kenoun (J/H) | K9: Total J/H | L9: Goulot (J/H) | M9: Durée (j. ouvrés) | N9: Début | O9: Fin | P9: Stories
A10: S01 | B10: Lot 1 | C10: Fondations | D10: Connexion avec rôle sur l'app mobile en Dev ; modèle de données validé avec l'IT SIVO. | E10: =F10+G10 -> 6.5 | F10: =SUMIFS(Backlog!$K:$K,Backlog!$N:$N,$A10,Backlog!$H:$H,"Front Mobile",Backlog!$B:$B,"Sous-tâche") -> 6.5 | G10: =SUMIFS(Backlog!$K:$K,Backlog!$N:$N,$A10,Backlog!$H:$H,"Front Web",Backlog!$B:$B,"Sous-tâche") -> 0 | H10: =SUMIFS(Backlog!$K:$K,Backlog!$N:$N,$A10,Backlog!$H:$H,"Back",Backlog!$B:$B,"Sous-tâche") -> 12 | I10: =SUMIFS(Backlog!$K:$K,Backlog!$N:$N,$A10,Backlog!$H:$H,"IA",Backlog!$B:$B,"Sous-tâche") -> 0 | J10: =SUMIFS(Backlog!$K:$K,Backlog!$N:$N,$A10,Backlog!$H:$H,"DevOps",Backlog!$B:$B,"Sous-tâche") -> 7 | K10: =E10+H10+I10+J10 -> 25.5 | L10: =MAX(E10,H10,I10,J10) -> 12 | M10: =ROUNDUP(L10/$B$6,0)+$B$5 -> 13 | N10: =WORKDAY($B$4-1,1) -> 46300 | O10: =WORKDAY(N10,M10-1) -> 46316 | P10: US-59, US-01, US-02, US-03, US-04, US-10
A11: S02 | B11: Lot 1 | C11: Intégration Oracle, sécurité & comptes | D11: Lecture/écriture sécurisée dans le SI SIVO ; l'opticien configure ses sites et crée ses vendeurs ; builds mobiles distribués. | E11: =F11+G11 -> 3.5 | F11: =SUMIFS(Backlog!$K:$K,Backlog!$N:$N,$A11,Backlog!$H:$H,"Front Mobile",Backlog!$B:$B,"Sous-tâche") -> 3.5 | G11: =SUMIFS(Backlog!$K:$K,Backlog!$N:$N,$A11,Backlog!$H:$H,"Front Web",Backlog!$B:$B,"Sous-tâche") -> 0 | H11: =SUMIFS(Backlog!$K:$K,Backlog!$N:$N,$A11,Backlog!$H:$H,"Back",Backlog!$B:$B,"Sous-tâche") -> 16.5 | I11: =SUMIFS(Backlog!$K:$K,Backlog!$N:$N,$A11,Backlog!$H:$H,"IA",Backlog!$B:$B,"Sous-tâche") -> 0 | J11: =SUMIFS(Backlog!$K:$K,Backlog!$N:$N,$A11,Backlog!$H:$H,"DevOps",Backlog!$B:$B,"Sous-tâche") -> 6.5 | K11: =E11+H11+I11+J11 -> 26.5 | L11: =MAX(E11,H11,I11,J11) -> 16.5 | M11: =ROUNDUP(L11/$B$6,0)+$B$5 -> 18 | N11: =WORKDAY(O10,1) -> 46317 | O11: =WORKDAY(N11,M11-1) -> 46342 | P11: US-60, US-05, US-06, US-08, US-51, US-52
A12: S03 | B12: Lot 1 | C12: Accès vendeurs & catalogue | D12: Vendeurs limités par site, jours et heures ; recherche catalogue et commande Stock sur mobile ; CI/CD complète. | E12: =F12+G12 -> 9.5 | F12: =SUMIFS(Backlog!$K:$K,Backlog!$N:$N,$A12,Backlog!$H:$H,"Front Mobile",Backlog!$B:$B,"Sous-tâche") -> 9.5 | G12: =SUMIFS(Backlog!$K:$K,Backlog!$N:$N,$A12,Backlog!$H:$H,"Front Web",Backlog!$B:$B,"Sous-tâche") -> 0 | H12: =SUMIFS(Backlog!$K:$K,Backlog!$N:$N,$A12,Backlog!$H:$H,"Back",Backlog!$B:$B,"Sous-tâche") -> 14.5 | I12: =SUMIFS(Backlog!$K:$K,Backlog!$N:$N,$A12,Backlog!$H:$H,"IA",Backlog!$B:$B,"Sous-tâche") -> 0 | J12: =SUMIFS(Backlog!$K:$K,Backlog!$N:$N,$A12,Backlog!$H:$H,"DevOps",Backlog!$B:$B,"Sous-tâche") -> 6 | K12: =E12+H12+I12+J12 -> 30 | L12: =MAX(E12,H12,I12,J12) -> 14.5 | M12: =ROUNDUP(L12/$B$6,0)+$B$5 -> 16 | N12: =WORKDAY(O11,1) -> 46343 | O12: =WORKDAY(N12,M12-1) -> 46364 | P12: US-11, US-53, US-54, US-12, US-13
A13: S04 | B13: Lot 1 | C13: Commande RX & suivi | D13: Commande RX guidée (monture, options) transmise à SIVO et suivie ; tests d'intégration Oracle. | E13: =F13+G13 -> 7.5 | F13: =SUMIFS(Backlog!$K:$K,Backlog!$N:$N,$A13,Backlog!$H:$H,"Front Mobile",Backlog!$B:$B,"Sous-tâche") -> 7.5 | G13: =SUMIFS(Backlog!$K:$K,Backlog!$N:$N,$A13,Backlog!$H:$H,"Front Web",Backlog!$B:$B,"Sous-tâche") -> 0 | H13: =SUMIFS(Backlog!$K:$K,Backlog!$N:$N,$A13,Backlog!$H:$H,"Back",Backlog!$B:$B,"Sous-tâche") -> 14 | I13: =SUMIFS(Backlog!$K:$K,Backlog!$N:$N,$A13,Backlog!$H:$H,"IA",Backlog!$B:$B,"Sous-tâche") -> 0 | J13: =SUMIFS(Backlog!$K:$K,Backlog!$N:$N,$A13,Backlog!$H:$H,"DevOps",Backlog!$B:$B,"Sous-tâche") -> 0 | K13: =E13+H13+I13+J13 -> 21.5 | L13: =MAX(E13,H13,I13,J13) -> 14 | M13: =ROUNDUP(L13/$B$6,0)+$B$5 -> 15 | N13: =WORKDAY(O12,1) -> 46365 | O13: =WORKDAY(N13,M13-1) -> 46385 | P13: US-07, US-14, US-15, US-45, US-16, US-17
A14: S05 | B14: Lot 1 | C14: Précal digital (saisie) | D14: Un opticien envoie un bon précal complet, contrôlé et horodaté depuis le mobile ; audit des actions sensibles. | E14: =F14+G14 -> 9.5 | F14: =SUMIFS(Backlog!$K:$K,Backlog!$N:$N,$A14,Backlog!$H:$H,"Front Mobile",Backlog!$B:$B,"Sous-tâche") -> 9.5 | G14: =SUMIFS(Backlog!$K:$K,Backlog!$N:$N,$A14,Backlog!$H:$H,"Front Web",Backlog!$B:$B,"Sous-tâche") -> 0 | H14: =SUMIFS(Backlog!$K:$K,Backlog!$N:$N,$A14,Backlog!$H:$H,"Back",Backlog!$B:$B,"Sous-tâche") -> 12.5 | I14: =SUMIFS(Backlog!$K:$K,Backlog!$N:$N,$A14,Backlog!$H:$H,"IA",Backlog!$B:$B,"Sous-tâche") -> 0 | J14: =SUMIFS(Backlog!$K:$K,Backlog!$N:$N,$A14,Backlog!$H:$H,"DevOps",Backlog!$B:$B,"Sous-tâche") -> 0 | K14: =E14+H14+I14+J14 -> 22 | L14: =MAX(E14,H14,I14,J14) -> 12.5 | M14: =ROUNDUP(L14/$B$6,0)+$B$5 -> 14 | N14: =WORKDAY(O13,1) -> 46386 | O14: =WORKDAY(N14,M14-1) -> 46405 | P14: US-09, US-20, US-21, US-47
A15: S06 | B15: Lot 1 | C15: Précal SIVO, notifications & réclamations | D15: SIVO traite le précal en back-office ; l'opticien est notifié et déclare une réclamation. | E15: =F15+G15 -> 9 | F15: =SUMIFS(Backlog!$K:$K,Backlog!$N:$N,$A15,Backlog!$H:$H,"Front Mobile",Backlog!$B:$B,"Sous-tâche") -> 6 | G15: =SUMIFS(Backlog!$K:$K,Backlog!$N:$N,$A15,Backlog!$H:$H,"Front Web",Backlog!$B:$B,"Sous-tâche") -> 3 | H15: =SUMIFS(Backlog!$K:$K,Backlog!$N:$N,$A15,Backlog!$H:$H,"Back",Backlog!$B:$B,"Sous-tâche") -> 12 | I15: =SUMIFS(Backlog!$K:$K,Backlog!$N:$N,$A15,Backlog!$H:$H,"IA",Backlog!$B:$B,"Sous-tâche") -> 2.5 | J15: =SUMIFS(Backlog!$K:$K,Backlog!$N:$N,$A15,Backlog!$H:$H,"DevOps",Backlog!$B:$B,"Sous-tâche") -> 0.5 | K15: =E15+H15+I15+J15 -> 24 | L15: =MAX(E15,H15,I15,J15) -> 12 | M15: =ROUNDUP(L15/$B$6,0)+$B$5 -> 13 | N15: =WORKDAY(O14,1) -> 46406 | O15: =WORKDAY(N15,M15-1) -> 46422 | P15: US-48, US-49, US-46, US-24, US-28
A16: S07 | B16: Lot 1 | C16: Réclamations, permissions vendeurs & stores | D16: Réclamation traitée jusqu'à la clôture ; permissions vendeurs ; app publiée. Recette mobile Lot 1. | E16: =F16+G16 -> 7.5 | F16: =SUMIFS(Backlog!$K:$K,Backlog!$N:$N,$A16,Backlog!$H:$H,"Front Mobile",Backlog!$B:$B,"Sous-tâche") -> 4.5 | G16: =SUMIFS(Backlog!$K:$K,Backlog!$N:$N,$A16,Backlog!$H:$H,"Front Web",Backlog!$B:$B,"Sous-tâche") -> 3 | H16: =SUMIFS(Backlog!$K:$K,Backlog!$N:$N,$A16,Backlog!$H:$H,"Back",Backlog!$B:$B,"Sous-tâche") -> 12 | I16: =SUMIFS(Backlog!$K:$K,Backlog!$N:$N,$A16,Backlog!$H:$H,"IA",Backlog!$B:$B,"Sous-tâche") -> 5.5 | J16: =SUMIFS(Backlog!$K:$K,Backlog!$N:$N,$A16,Backlog!$H:$H,"DevOps",Backlog!$B:$B,"Sous-tâche") -> 1.5 | K16: =E16+H16+I16+J16 -> 26.5 | L16: =MAX(E16,H16,I16,J16) -> 12 | M16: =ROUNDUP(L16/$B$6,0)+$B$5 -> 13 | N16: =WORKDAY(O15,1) -> 46423 | O16: =WORKDAY(N16,M16-1) -> 46441 | P16: US-61, US-55, US-25, US-26, US-27, US-31
A17: S08 | B17: Lot 2 | C17: Favoris, tracking & espace commercial | D17: Commande depuis favoris, décharge électronique, représentant qui commande pour son client. Recette mobile Lot 2. | E17: =F17+G17 -> 11 | F17: =SUMIFS(Backlog!$K:$K,Backlog!$N:$N,$A17,Backlog!$H:$H,"Front Mobile",Backlog!$B:$B,"Sous-tâche") -> 11 | G17: =SUMIFS(Backlog!$K:$K,Backlog!$N:$N,$A17,Backlog!$H:$H,"Front Web",Backlog!$B:$B,"Sous-tâche") -> 0 | H17: =SUMIFS(Backlog!$K:$K,Backlog!$N:$N,$A17,Backlog!$H:$H,"Back",Backlog!$B:$B,"Sous-tâche") -> 14 | I17: =SUMIFS(Backlog!$K:$K,Backlog!$N:$N,$A17,Backlog!$H:$H,"IA",Backlog!$B:$B,"Sous-tâche") -> 0 | J17: =SUMIFS(Backlog!$K:$K,Backlog!$N:$N,$A17,Backlog!$H:$H,"DevOps",Backlog!$B:$B,"Sous-tâche") -> 0 | K17: =E17+H17+I17+J17 -> 25 | L17: =MAX(E17,H17,I17,J17) -> 14 | M17: =ROUNDUP(L17/$B$6,0)+$B$5 -> 15 | N17: =WORKDAY(O16,1) -> 46442 | O17: =WORKDAY(N17,M17-1) -> 46462 | P17: US-18, US-19, US-22, US-23, US-56, US-57, US-58
A18: S09 | B18: Lot 3 + Web | C18: Recommandation & socle web | D18: Verre recommandé justifié ; le web démarre : connexion, rôles, vendeurs. | E18: =F18+G18 -> 8.5 | F18: =SUMIFS(Backlog!$K:$K,Backlog!$N:$N,$A18,Backlog!$H:$H,"Front Mobile",Backlog!$B:$B,"Sous-tâche") -> 1.5 | G18: =SUMIFS(Backlog!$K:$K,Backlog!$N:$N,$A18,Backlog!$H:$H,"Front Web",Backlog!$B:$B,"Sous-tâche") -> 7 | H18: =SUMIFS(Backlog!$K:$K,Backlog!$N:$N,$A18,Backlog!$H:$H,"Back",Backlog!$B:$B,"Sous-tâche") -> 2 | I18: =SUMIFS(Backlog!$K:$K,Backlog!$N:$N,$A18,Backlog!$H:$H,"IA",Backlog!$B:$B,"Sous-tâche") -> 6.5 | J18: =SUMIFS(Backlog!$K:$K,Backlog!$N:$N,$A18,Backlog!$H:$H,"DevOps",Backlog!$B:$B,"Sous-tâche") -> 1 | K18: =E18+H18+I18+J18 -> 18 | L18: =MAX(E18,H18,I18,J18) -> 8.5 | M18: =ROUNDUP(L18/$B$6,0)+$B$5 -> 10 | N18: =WORKDAY(O17,1) -> 46463 | O18: =WORKDAY(N18,M18-1) -> 46476 | P18: US-W00, US-W01, US-W02, US-W03, US-29, US-30
A19: S10 | B19: Lot 3 + Web | C19: Chatbot IA & commande web | D19: Chatbot complet sur mobile ; commande Stock/RX sur le web. | E19: =F19+G19 -> 11 | F19: =SUMIFS(Backlog!$K:$K,Backlog!$N:$N,$A19,Backlog!$H:$H,"Front Mobile",Backlog!$B:$B,"Sous-tâche") -> 4.5 | G19: =SUMIFS(Backlog!$K:$K,Backlog!$N:$N,$A19,Backlog!$H:$H,"Front Web",Backlog!$B:$B,"Sous-tâche") -> 6.5 | H19: =SUMIFS(Backlog!$K:$K,Backlog!$N:$N,$A19,Backlog!$H:$H,"Back",Backlog!$B:$B,"Sous-tâche") -> 7.5 | I19: =SUMIFS(Backlog!$K:$K,Backlog!$N:$N,$A19,Backlog!$H:$H,"IA",Backlog!$B:$B,"Sous-tâche") -> 11 | J19: =SUMIFS(Backlog!$K:$K,Backlog!$N:$N,$A19,Backlog!$H:$H,"DevOps",Backlog!$B:$B,"Sous-tâche") -> 0 | K19: =E19+H19+I19+J19 -> 29.5 | L19: =MAX(E19,H19,I19,J19) -> 11 | M19: =ROUNDUP(L19/$B$6,0)+$B$5 -> 12 | N19: =WORKDAY(O18,1) -> 46477 | O19: =WORKDAY(N19,M19-1) -> 46492 | P19: US-W04, US-32, US-33, US-34, US-35, US-50
A20: S11 | B20: Lot 3 + Web | C20: Qualité IA, supervision & web Lot 1 | D20: Seuils IA atteints, tests d'injection passés, supervision active ; Lot 1 complet sur le web. | E20: =F20+G20 -> 10 | F20: =SUMIFS(Backlog!$K:$K,Backlog!$N:$N,$A20,Backlog!$H:$H,"Front Mobile",Backlog!$B:$B,"Sous-tâche") -> 0 | G20: =SUMIFS(Backlog!$K:$K,Backlog!$N:$N,$A20,Backlog!$H:$H,"Front Web",Backlog!$B:$B,"Sous-tâche") -> 10 | H20: =SUMIFS(Backlog!$K:$K,Backlog!$N:$N,$A20,Backlog!$H:$H,"Back",Backlog!$B:$B,"Sous-tâche") -> 6.5 | I20: =SUMIFS(Backlog!$K:$K,Backlog!$N:$N,$A20,Backlog!$H:$H,"IA",Backlog!$B:$B,"Sous-tâche") -> 12.5 | J20: =SUMIFS(Backlog!$K:$K,Backlog!$N:$N,$A20,Backlog!$H:$H,"DevOps",Backlog!$B:$B,"Sous-tâche") -> 10 | K20: =E20+H20+I20+J20 -> 39 | L20: =MAX(E20,H20,I20,J20) -> 12.5 | M20: =ROUNDUP(L20/$B$6,0)+$B$5 -> 14 | N20: =WORKDAY(O19,1) -> 46493 | O20: =WORKDAY(N20,M20-1) -> 46512 | P20: US-W05, US-W06, US-W07, US-36, US-37, US-38, US-39, US-40
A21: S12 | B21: Lots 2-3 + Web | C21: Web Lots 2-3, sauvegarde & transfert | D21: Web complet ; restauration testée ; IT SIVO autonome. Recette finale. | E21: =F21+G21 -> 9 | F21: =SUMIFS(Backlog!$K:$K,Backlog!$N:$N,$A21,Backlog!$H:$H,"Front Mobile",Backlog!$B:$B,"Sous-tâche") -> 0 | G21: =SUMIFS(Backlog!$K:$K,Backlog!$N:$N,$A21,Backlog!$H:$H,"Front Web",Backlog!$B:$B,"Sous-tâche") -> 9 | H21: =SUMIFS(Backlog!$K:$K,Backlog!$N:$N,$A21,Backlog!$H:$H,"Back",Backlog!$B:$B,"Sous-tâche") -> 1.5 | I21: =SUMIFS(Backlog!$K:$K,Backlog!$N:$N,$A21,Backlog!$H:$H,"IA",Backlog!$B:$B,"Sous-tâche") -> 2 | J21: =SUMIFS(Backlog!$K:$K,Backlog!$N:$N,$A21,Backlog!$H:$H,"DevOps",Backlog!$B:$B,"Sous-tâche") -> 9.5 | K21: =E21+H21+I21+J21 -> 22 | L21: =MAX(E21,H21,I21,J21) -> 9.5 | M21: =ROUNDUP(L21/$B$6,0)+$B$5 -> 11 | N21: =WORKDAY(O20,1) -> 46513 | O21: =WORKDAY(N21,M21-1) -> 46527 | P21: US-W08, US-W09, US-W10, US-W11, US-W12, US-41, US-42, US-43, US-44
A22: TOTAL | E22: =SUM(E10:E21) -> 102.5 | F22: =SUM(F10:F21) -> 64 | G22: =SUM(G10:G21) -> 38.5 | H22: =SUM(H10:H21) -> 125 | I22: =SUM(I10:I21) -> 40 | J22: =SUM(J10:J21) -> 42 | K22: =SUM(K10:K21) -> 309.5 | L22: =SUM(L10:L21) -> 149 | M22: =SUM(M10:M21) -> 164 | N22: =N10 -> 46300 | O22: =O21 -> 46527
A24: Contrôle de l'échéance
A25: Fin estimée du projet | D25: =O22 -> 46527
A26: Échéance CDC | D26: =$B$7 -> 46444
A27: Écart (jours ouvrés, + = retard) | D27: =NETWORKDAYS($B$7,O22)-1 -> 59
A28: Statut | D28: =IF(O22<=$B$7,"Dans les temps","RETARD — voir leviers ci-dessous") -> RETARD — voir leviers ci-dessous
A30: Taux d'occupation par personne (charge / jours ouvrés hors cérémonies)
E31: Youssef Feki (Front) | F31: Ahmed Jmal (Back) | G31: Yessine Affes (IA) | H31: Heni Kenoun (DevOps)
E32: =E22/(M22-$B$5*12) -> 0.67434211 | F32: =H22/(M22-$B$5*12) -> 0.82236842 | G32: =I22/(M22-$B$5*12) -> 0.26315789 | H32: =J22/(M22-$B$5*12) -> 0.27631579
A33: Back = personne la plus chargée (~121 J/H) : il porte le backend ET la base de données ; il est le goulot des 8 premiers sprints.

Sheet Backlog
A1: Clé | B1: Type | C1: Lot | D1: Épic | E1: Parent | F1: Résumé | G1: User story & critères d'acceptation | H1: Rôle | I1: Personne (équipe) | J1: Assigné | K1: Estimation J/H | L1: Story points | M1: Priorité | N1: Sprint | O1: Source charge | P1: Dépendances | Q1: Statut | R1: Réf. devis / CDC | S1: Réf. équipe (Jira OPT / rapport) | T1: Constat du rapprochement
A2: E20 | B2: Epic | C2: Lot 1 | D2: E20 | F2: Socle application mobile (iOS / Android) | G2: Objectif : Disposer d'une application mobile iOS/Android branchée sur le backend unique. Réf. : Hors devis — CDC v2 multi-canal (avenant) | K2: =SUMIFS($K:$K,$D:$D,A2,$B:$B,"Sous-tâche") -> 13 | L2: =SUMIFS($L:$L,$D:$D,A2,$B:$B,"Story") -> 26 | M2: Highest | P2: E05 | Q2: =IF(COUNTIFS($D:$D,A2,$B:$B,"Sous-tâche")=0,"To Do",IF(COUNTIFS($D:$D,A2,$B:$B,"Sous-tâche",$Q:$Q,"Done")=COUNTIFS($D:$D,A2,$B:$B,"Sous-tâche"),"Done",IF(COUNTIFS($D:$D,A2,$B:$B,"Sous-tâche",$Q:$Q,"To Do")=COUNTIFS($D:$D,A2,$B:$B,"Sous-tâche"),"To Do","In Progress"))) -> In Progress | R2: Hors devis — CDC v2 multi-canal (avenant)
A3: US-59 | B3: Story | C3: Lot 1 | D3: E20 | E3: E20 | F3: Initialisation de l'application mobile | G3: En tant qu'équipe projet, je veux une base d'application mobile partagée iOS / Android, afin de développer chaque écran une seule fois. Critères d'acceptation : • Projet cross-platform (React Native ou Flutter — à valider), navigation, thème / design system. • Client API unique partagé avec le futur front web. | H3: Front Mobile | I3: Front | J3: Youssef Feki | K3: =SUMIFS($K:$K,$E:$E,A3,$B:$B,"Sous-tâche") -> 4 | L3: 8 | M3: Highest | N3: S01 | O3: À valider | P3: E05 | Q3: =IF(COUNTIFS($E:$E,A3,$B:$B,"Sous-tâche")=0,"To Do",IF(COUNTIFS($E:$E,A3,$B:$B,"Sous-tâche",$Q:$Q,"Done")=COUNTIFS($E:$E,A3,$B:$B,"Sous-tâche"),"Done",IF(COUNTIFS($E:$E,A3,$B:$B,"Sous-tâche",$Q:$Q,"To Do")=COUNTIFS($E:$E,A3,$B:$B,"Sous-tâche"),"To Do","In Progress"))) -> In Progress | R3: Hors devis — CDC v2 multi-canal (avenant)
A4: US-59-T1 | B4: Sous-tâche | C4: Lot 1 | D4: E20 | E4: US-59 | F4: [Front Mobile] Initialisation projet, navigation, design system | H4: Front Mobile | I4: Front | J4: Youssef Feki | K4: 3 | M4: Highest | N4: S01 | O4: À valider | Q4: Done | R4: Hors devis — CDC v2 multi-canal (avenant) | S4: Rapport Front §2-3A | T4: React Native 0.87 + TypeScript, Clean Architecture, thème clair/sombre, police Manrope, charte OptiVo.
A5: US-59-T2 | B5: Sous-tâche | C5: Lot 1 | D5: E20 | E5: US-59 | F5: [Front Mobile] Client API typé + gestion des erreurs et du mode hors ligne | H5: Front Mobile | I5: Front | J5: Youssef Feki | K5: 1 | M5: Highest | N5: S01 | O5: À valider | Q5: In Progress | R5: Hors devis — CDC v2 multi-canal (avenant) | S5: Rapport Front §3A-3C | T5: Client API + validation env faits ; mode hors ligne prévu (prochaine étape 02).
A6: US-60 | B6: Story | C6: Lot 1 | D6: E20 | E6: E20 | F6: Build et distribution mobile | G6: En tant que PO, je veux recevoir chaque version mobile sur mon téléphone, afin de recetter sur appareil réel. Critères d'acceptation : • Build iOS et Android automatiques dans la CI. • Distribution de recette (TestFlight / Play internal testing). | H6: DevOps | I6: DevOps | J6: Heni Kenoun | K6: =SUMIFS($K:$K,$E:$E,A6,$B:$B,"Sous-tâche") -> 3 | L6: 5 | M6: High | N6: S02 | O6: À valider | P6: E05 | Q6: =IF(COUNTIFS($E:$E,A6,$B:$B,"Sous-tâche")=0,"To Do",IF(COUNTIFS($E:$E,A6,$B:$B,"Sous-tâche",$Q:$Q,"Done")=COUNTIFS($E:$E,A6,$B:$B,"Sous-tâche"),"Done",IF(COUNTIFS($E:$E,A6,$B:$B,"Sous-tâche",$Q:$Q,"To Do")=COUNTIFS($E:$E,A6,$B:$B,"Sous-tâche"),"To Do","In Progress"))) -> To Do | R6: Hors devis — CDC v2 multi-canal (avenant)
A7: US-60-T1 | B7: Sous-tâche | C7: Lot 1 | D7: E20 | E7: US-60 | F7: [DevOps] Pipeline de build mobile + signature des applications | H7: DevOps | I7: DevOps | J7: Heni Kenoun | K7: 2 | M7: High | N7: S02 | O7: À valider | Q7: To Do | R7: Hors devis — CDC v2 multi-canal (avenant)
A8: US-60-T2 | B8: Sous-tâche | C8: Lot 1 | D8: E20 | E8: US-60 | F8: [DevOps] Distribution TestFlight / Google Play (test interne) | H8: DevOps | I8: DevOps | J8: Heni Kenoun | K8: 1 | M8: High | N8: S02 | O8: À valider | Q8: To Do | R8: Hors devis — CDC v2 multi-canal (avenant)
A9: US-61 | B9: Story | C9: Lot 1 | D9: E20 | E9: E20 | F9: Publication sur les stores | G9: En tant qu'opticien, je veux télécharger l'application sur l'App Store et Google Play, afin de l'utiliser sur mon téléphone. Critères d'acceptation : • Fiches store, captures, politique de confidentialité prêtes. • Application validée par Apple et Google. | H9: Front Mobile, DevOps | I9: Front, DevOps | J9: Heni Kenoun | K9: =SUMIFS($K:$K,$E:$E,A9,$B:$B,"Sous-tâche") -> 2.5 | L9: 5 | M9: High | N9: S07 | O9: À valider | P9: E05 | Q9: =IF(COUNTIFS($E:$E,A9,$B:$B,"Sous-tâche")=0,"To Do",IF(COUNTIFS($E:$E,A9,$B:$B,"Sous-tâche",$Q:$Q,"Done")=COUNTIFS($E:$E,A9,$B:$B,"Sous-tâche"),"Done",IF(COUNTIFS($E:$E,A9,$B:$B,"Sous-tâche",$Q:$Q,"To Do")=COUNTIFS($E:$E,A9,$B:$B,"Sous-tâche"),"To Do","In Progress"))) -> To Do | R9: Hors devis — CDC v2 multi-canal (avenant)
A10: US-61-T1 | B10: Sous-tâche | C10: Lot 1 | D10: E20 | E10: US-61 | F10: [DevOps] Comptes développeur, fiches store, soumission | H10: DevOps | I10: DevOps | J10: Heni Kenoun | K10: 1.5 | M10: High | N10: S07 | O10: À valider | Q10: To Do | R10: Hors devis — CDC v2 multi-canal (avenant)
A11: US-61-T2 | B11: Sous-tâche | C11: Lot 1 | D11: E20 | E11: US-61 | F11: [Front Mobile] Ajustements de conformité store (permissions, écrans) | H11: Front Mobile | I11: Front | J11: Youssef Feki | K11: 1 | M11: High | N11: S07 | O11: À valider | Q11: To Do | R11: Hors devis — CDC v2 multi-canal (avenant)
A12: US-W00 | B12: Story | C12: Lot 1 | D12: E20 | E12: E20 | F12: Socle front web (réutilise le client API mobile) | G12: En tant qu'équipe projet, je veux une base web qui réutilise le client API et le design system du mobile, afin de décliner les écrans rapidement. Critères d'acceptation : • Projet web initialisé, responsive, branché sur le même backend. • Build web intégré au pipeline. | H12: Front Web, DevOps | I12: Front, DevOps | J12: Youssef Feki | K12: =SUMIFS($K:$K,$E:$E,A12,$B:$B,"Sous-tâche") -> 3.5 | L12: 8 | M12: High | N12: S09 | O12: À valider | P12: E05 | Q12: =IF(COUNTIFS($E:$E,A12,$B:$B,"Sous-tâche")=0,"To Do",IF(COUNTIFS($E:$E,A12,$B:$B,"Sous-tâche",$Q:$Q,"Done")=COUNTIFS($E:$E,A12,$B:$B,"Sous-tâche"),"Done",IF(COUNTIFS($E:$E,A12,$B:$B,"Sous-tâche",$Q:$Q,"To Do")=COUNTIFS($E:$E,A12,$B:$B,"Sous-tâche"),"To Do","In Progress"))) -> To Do | R12: Hors devis — CDC v2 multi-canal (avenant)
A13: US-W00-T1 | B13: Sous-tâche | C13: Lot 1 | D13: E20 | E13: US-W00 | F13: [Front Web] Initialisation projet web, layout responsive, design system partagé | H13: Front Web | I13: Front | J13: Youssef Feki | K13: 2 | M13: High | N13: S09 | O13: À valider | Q13: To Do | R13: Hors devis — CDC v2 multi-canal (avenant)
A14: US-W00-T2 | B14: Sous-tâche | C14: Lot 1 | D14: E20 | E14: US-W00 | F14: [Front Web] Intégration du build web au pipeline | H14: Front Web | I14: Front | J14: Youssef Feki | K14: 0.5 | M14: High | N14: S09 | O14: À valider | Q14: To Do | R14: Hors devis — CDC v2 multi-canal (avenant)
A15: US-W00-T3 | B15: Sous-tâche | C15: Lot 1 | D15: E20 | E15: US-W00 | F15: [DevOps] Hébergement et déploiement du front web | H15: DevOps | I15: DevOps | J15: Heni Kenoun | K15: 1 | M15: High | N15: S09 | O15: À valider | Q15: To Do | R15: Hors devis — CDC v2 multi-canal (avenant)
A16: E01 | B16: Epic | C16: Lot 1 | D16: E01 | F16: Authentification | G16: Objectif : Permettre aux utilisateurs d'accéder à l'application de manière sécurisée. Réf. : L1 – Socle technique / Tâche 1 | K16: =SUMIFS($K:$K,$D:$D,A16,$B:$B,"Sous-tâche") -> 7 | L16: =SUMIFS($L:$L,$D:$D,A16,$B:$B,"Story") -> 10 | M16: Highest | P16: Choix du mode d'authentification (comptes locaux / annuaire SIVO / SSO) | Q16: =IF(COUNTIFS($D:$D,A16,$B:$B,"Sous-tâche")=0,"To Do",IF(COUNTIFS($D:$D,A16,$B:$B,"Sous-tâche",$Q:$Q,"Done")=COUNTIFS($D:$D,A16,$B:$B,"Sous-tâche"),"Done",IF(COUNTIFS($D:$D,A16,$B:$B,"Sous-tâche",$Q:$Q,"To Do")=COUNTIFS($D:$D,A16,$B:$B,"Sous-tâche"),"To Do","In Progress"))) -> In Progress | R16: L1 – Socle technique / Tâche 1
A17: US-01 | B17: Story | C17: Lot 1 | D17: E01 | E17: E01 | F17: Connexion / déconnexion sécurisée | G17: En tant qu'opticien, je veux me connecter et me déconnecter de façon sécurisée, afin d'accéder à mon espace de commande. Critères d'acceptation : • Étant donné un compte actif, quand je saisis des identifiants valides, alors j'accède au tableau de bord en < 2 s. • Étant donné des identifiants invalides, alors un message générique s'affiche (sans préciser le champ en erreur). • La session expire après inactivité (durée à valider) et le jeton de rafraîchissement est révocable. • Après déconnexion, le bouton Retour du navigateur ne réaffiche aucune donnée. | H17: Front Mobile, Back | I17: Front, Back | J17: Ahmed Jmal | K17: =SUMIFS($K:$K,$E:$E,A17,$B:$B,"Sous-tâche") -> 4 | L17: 5 | M17: Highest | N17: S01 | O17: Devis | P17: Choix du mode d'authentification (comptes locaux / annuaire SIVO / SSO) | Q17: =IF(COUNTIFS($E:$E,A17,$B:$B,"Sous-tâche")=0,"To Do",IF(COUNTIFS($E:$E,A17,$B:$B,"Sous-tâche",$Q:$Q,"Done")=COUNTIFS($E:$E,A17,$B:$B,"Sous-tâche"),"Done",IF(COUNTIFS($E:$E,A17,$B:$B,"Sous-tâche",$Q:$Q,"To Do")=COUNTIFS($E:$E,A17,$B:$B,"Sous-tâche"),"To Do","In Progress"))) -> Done | R17: L1 – Socle technique / Tâche 1
A18: US-01-T1 | B18: Sous-tâche | C18: Lot 1 | D18: E01 | E18: US-01 | F18: [Back] API login / logout / refresh token (JWT) + expiration de session | H18: Back | I18: Back | J18: Ahmed Jmal | K18: 1.5 | M18: Highest | N18: S01 | O18: Devis | Q18: Done | R18: L1 – Socle technique / Tâche 1 | S18: OPT-102, OPT-103 | T18: Login / refresh / logout JWT stateless, Argon2id, profil revérifié à chaque refresh.
A19: US-01-T2 | B19: Sous-tâche | C19: Lot 1 | D19: E01 | E19: US-01 | F19: [Front Mobile] Écran de connexion mobile + gestion du jeton et redirections | H19: Front Mobile | I19: Front | J19: Youssef Feki | K19: 1 | M19: Highest | N19: S01 | O19: Devis | Q19: Done | R19: L1 – Socle technique / Tâche 1 | S19: Rapport Front §3B-3C | T19: LoginScreen, validation temps réel, auto-refresh JWT, reconnexion transparente, restauration de session.
A20: US-01-T3 | B20: Sous-tâche | C20: Lot 1 | D20: E01 | E20: US-01 | F20: [Back] Tables users / sessions / refresh_tokens | H20: Back | I20: Back | J20: Ahmed Jmal | K20: 0.5 | M20: Highest | N20: S01 | O20: Devis | Q20: Done | R20: L1 – Socle technique / Tâche 1 | S20: OPT-101, OPT-102 | T20: Modèle Prisma users / profils. Pas de table sessions (choix stateless, assumé).
A21: US-02 | B21: Story | C21: Lot 1 | D21: E01 | E21: E01 | F21: Mot de passe oublié & réinitialisation | G21: En tant qu'opticien, je veux réinitialiser mon mot de passe, afin de récupérer mon compte sans appeler le support. Critères d'acceptation : • Quand je demande une réinitialisation, alors je reçois un lien à usage unique valable 30 min. • Le nouveau mot de passe respecte la politique SIVO (longueur, complexité). • La réponse est identique que l'e-mail existe ou non (pas d'énumération de comptes). | H21: Front Mobile, Back | I21: Front, Back | J21: Ahmed Jmal | K21: =SUMIFS($K:$K,$E:$E,A21,$B:$B,"Sous-tâche") -> 2 | L21: 3 | M21: High | N21: S01 | O21: Devis | P21: Choix du mode d'authentification (comptes locaux / annuaire SIVO / SSO) | Q21: =IF(COUNTIFS($E:$E,A21,$B:$B,"Sous-tâche")=0,"To Do",IF(COUNTIFS($E:$E,A21,$B:$B,"Sous-tâche",$Q:$Q,"Done")=COUNTIFS($E:$E,A21,$B:$B,"Sous-tâche"),"Done",IF(COUNTIFS($E:$E,A21,$B:$B,"Sous-tâche",$Q:$Q,"To Do")=COUNTIFS($E:$E,A21,$B:$B,"Sous-tâche"),"To Do","In Progress"))) -> Done | R21: L1 – Socle technique / Tâche 1
A22: US-02-T1 | B22: Sous-tâche | C22: Lot 1 | D22: E01 | E22: US-02 | F22: [Back] Flux reset : génération jeton, envoi e-mail, validation | H22: Back | I22: Back | J22: Ahmed Jmal | K22: 1 | M22: High | N22: S01 | O22: Devis | Q22: Done | R22: L1 – Socle technique / Tâche 1 | S22: OPT-104 | T22: Écart vs critère : code OTP par e-mail au lieu d'un lien 30 min → critère à mettre à jour.
A23: US-02-T2 | B23: Sous-tâche | C23: Lot 1 | D23: E01 | E23: US-02 | F23: [Front Mobile] Écrans mot de passe oublié / nouveau mot de passe | H23: Front Mobile | I23: Front | J23: Youssef Feki | K23: 0.5 | M23: High | N23: S01 | O23: Devis | Q23: Done | R23: L1 – Socle technique / Tâche 1 | S23: Rapport Front §3D | T23: Flux 4 étapes avec OTP 6 chiffres (BottomSheet).
A24: US-02-T3 | B24: Sous-tâche | C24: Lot 1 | D24: E01 | E24: US-02 | F24: [Back] Tests automatisés du module d'authentification | H24: Back | I24: Back | J24: Ahmed Jmal | K24: 0.5 | M24: High | N24: S01 | O24: Devis | Q24: Done | R24: L1 – Socle technique / Tâche 1 | S24: OPT-302 | T24: Tests unitaires + E2E auth sur PostgreSQL réel et Mailpit.
A25: US-W01 | B25: Story | C25: Lot 1 | D25: E01 | E25: E01 | F25: Version web — Authentification | G25: En tant qu'utilisateur web, je veux retrouver sur navigateur les fonctions « Authentification » de l'application mobile, afin de travailler depuis mon poste. Critères d'acceptation : • Mêmes règles et mêmes API que la version mobile (aucune logique métier dupliquée). • Affichage correct sur Chrome, Edge, Safari, Firefox (2 dernières versions), de 1280 px à la tablette. • Critères d'acceptation des stories mobiles de l'épic re-vérifiés sur le web. | H25: Front Web | I25: Front | J25: Youssef Feki | K25: =SUMIFS($K:$K,$E:$E,A25,$B:$B,"Sous-tâche") -> 1 | L25: 2 | M25: Highest | N25: S09 | O25: À valider | P25: Choix du mode d'authentification (comptes locaux / annuaire SIVO / SSO) | Q25: =IF(COUNTIFS($E:$E,A25,$B:$B,"Sous-tâche")=0,"To Do",IF(COUNTIFS($E:$E,A25,$B:$B,"Sous-tâche",$Q:$Q,"Done")=COUNTIFS($E:$E,A25,$B:$B,"Sous-tâche"),"Done",IF(COUNTIFS($E:$E,A25,$B:$B,"Sous-tâche",$Q:$Q,"To Do")=COUNTIFS($E:$E,A25,$B:$B,"Sous-tâche"),"To Do","In Progress"))) -> To Do | R25: L1 – Socle technique / Tâche 1
A26: US-W01-T1 | B26: Sous-tâche | C26: Lot 1 | D26: E01 | E26: US-W01 | F26: [Front Web] Écrans connexion / mot de passe oublié (web) | H26: Front Web | I26: Front | J26: Youssef Feki | K26: 1 | M26: Highest | N26: S09 | O26: À valider | Q26: To Do | R26: L1 – Socle technique / Tâche 1
A27: E02 | B27: Epic | C27: Lot 1 | D27: E02 | F27: Gestion des accès et des rôles | G27: Objectif : Contrôler ce que chaque profil peut consulter ou modifier. Réf. : L1 – Socle technique / Tâche 1 | K27: =SUMIFS($K:$K,$D:$D,A27,$B:$B,"Sous-tâche") -> 3 | L27: =SUMIFS($L:$L,$D:$D,A27,$B:$B,"Story") -> 6 | M27: Highest | P27: E01 | Q27: =IF(COUNTIFS($D:$D,A27,$B:$B,"Sous-tâche")=0,"To Do",IF(COUNTIFS($D:$D,A27,$B:$B,"Sous-tâche",$Q:$Q,"Done")=COUNTIFS($D:$D,A27,$B:$B,"Sous-tâche"),"Done",IF(COUNTIFS($D:$D,A27,$B:$B,"Sous-tâche",$Q:$Q,"To Do")=COUNTIFS($D:$D,A27,$B:$B,"Sous-tâche"),"To Do","In Progress"))) -> In Progress | R27: L1 – Socle technique / Tâche 1
A28: US-03 | B28: Story | C28: Lot 1 | D28: E02 | E28: E02 | F28: Matrice des rôles et contrôle d'accès | G28: En tant qu'administrateur SIVO, je veux attribuer un rôle à chaque utilisateur, afin que chacun n'accède qu'aux écrans et données autorisés. Critères d'acceptation : • La matrice rôles × permissions est validée par SIVO avant développement (DoR). • Étant donné un opticien, quand il appelle l'API d'un autre opticien, alors il reçoit 403. • Les menus et boutons non autorisés sont masqués côté front ET bloqués côté API. | H28: Front Mobile, Back | I28: Front, Back | J28: Ahmed Jmal | K28: =SUMIFS($K:$K,$E:$E,A28,$B:$B,"Sous-tâche") -> 2.5 | L28: 5 | M28: Highest | N28: S01 | O28: Mixte | P28: E01 | Q28: =IF(COUNTIFS($E:$E,A28,$B:$B,"Sous-tâche")=0,"To Do",IF(COUNTIFS($E:$E,A28,$B:$B,"Sous-tâche",$Q:$Q,"Done")=COUNTIFS($E:$E,A28,$B:$B,"Sous-tâche"),"Done",IF(COUNTIFS($E:$E,A28,$B:$B,"Sous-tâche",$Q:$Q,"To Do")=COUNTIFS($E:$E,A28,$B:$B,"Sous-tâche"),"To Do","In Progress"))) -> In Progress | R28: L1 – Socle technique / Tâche 1
A29: US-03-T1 | B29: Sous-tâche | C29: Lot 1 | D29: E02 | E29: US-03 | F29: [Back] Modèle RBAC : roles, permissions, user_roles | H29: Back | I29: Back | J29: Ahmed Jmal | K29: 0.5 | M29: Highest | N29: S01 | O29: Devis | Q29: In Progress | R29: L1 – Socle technique / Tâche 1 | S29: OPT-102, OPT-103 | T29: Profils OPTICIEN / VENDEUR (profileType) ; matrice permissions complète non faite.
A30: US-03-T2 | B30: Sous-tâche | C30: Lot 1 | D30: E02 | E30: US-03 | F30: [Back] Middleware d'autorisation + cloisonnement par opticien | H30: Back | I30: Back | J30: Ahmed Jmal | K30: 1 | M30: Highest | N30: S01 | O30: Devis | Q30: In Progress | R30: L1 – Socle technique / Tâche 1 | S30: OPT-103, OPT-207 | T30: JwtAccessGuard + OpticienOnlyGuard + isolation multi-tenant ; à étendre aux autres modules.
A31: US-03-T3 | B31: Sous-tâche | C31: Lot 1 | D31: E02 | E31: US-03 | F31: [Front Mobile] Guards de routes et masquage conditionnel des actions | H31: Front Mobile | I31: Front | J31: Youssef Feki | K31: 0.5 | M31: Highest | N31: S01 | O31: Devis | Q31: In Progress | R31: L1 – Socle technique / Tâche 1 | S31: Rapport Front §3E | T31: Distinction OPTICIEN / VENDEUR à l'accueil ; masquage des actions à faire quand les écrans métier existeront.
A32: US-03-T4 | B32: Sous-tâche | C32: Lot 1 | D32: E02 | E32: US-03 | F32: [Back] Rôles Vendeur et Commercial dans la matrice RBAC | H32: Back | I32: Back | J32: Ahmed Jmal | K32: 0.5 | M32: Highest | N32: S01 | O32: À valider | Q32: In Progress | R32: L1 – Socle technique / Tâche 1 | S32: OPT-201..207 | T32: Rôle Vendeur fait ; rôle Commercial à faire.
A33: US-W02 | B33: Story | C33: Lot 1 | D33: E02 | E33: E02 | F33: Version web — Gestion des accès et des rôles | G33: En tant qu'utilisateur web, je veux retrouver sur navigateur les fonctions « Gestion des accès et des rôles » de l'application mobile, afin de travailler depuis mon poste. Critères d'acceptation : • Mêmes règles et mêmes API que la version mobile (aucune logique métier dupliquée). • Affichage correct sur Chrome, Edge, Safari, Firefox (2 dernières versions), de 1280 px à la tablette. • Critères d'acceptation des stories mobiles de l'épic re-vérifiés sur le web. | H33: Front Web | I33: Front | J33: Youssef Feki | K33: =SUMIFS($K:$K,$E:$E,A33,$B:$B,"Sous-tâche") -> 0.5 | L33: 1 | M33: Highest | N33: S09 | O33: À valider | P33: E01 | Q33: =IF(COUNTIFS($E:$E,A33,$B:$B,"Sous-tâche")=0,"To Do",IF(COUNTIFS($E:$E,A33,$B:$B,"Sous-tâche",$Q:$Q,"Done")=COUNTIFS($E:$E,A33,$B:$B,"Sous-tâche"),"Done",IF(COUNTIFS($E:$E,A33,$B:$B,"Sous-tâche",$Q:$Q,"To Do")=COUNTIFS($E:$E,A33,$B:$B,"Sous-tâche"),"To Do","In Progress"))) -> To Do | R33: L1 – Socle technique / Tâche 1
A34: US-W02-T1 | B34: Sous-tâche | C34: Lot 1 | D34: E02 | E34: US-W02 | F34: [Front Web] Guards de routes et masquage des actions (web) | H34: Front Web | I34: Front | J34: Youssef Feki | K34: 0.5 | M34: Highest | N34: S09 | O34: À valider | Q34: To Do | R34: L1 – Socle technique / Tâche 1
A35: E03 | B35: Epic | C35: Lot 1 | D35: E03 | F35: Base de données partagée & intégration SIVO | G35: Objectif : Partager les données avec l'IT SIVO et rester cohérent avec le système de production Oracle existant. Réf. : L1 – Socle technique / Tâche 1 | K35: =SUMIFS($K:$K,$D:$D,A35,$B:$B,"Sous-tâche") -> 18 | L35: =SUMIFS($L:$L,$D:$D,A35,$B:$B,"Story") -> 36 | M35: Highest | P35: Accès réseau / base SIVO | Q35: =IF(COUNTIFS($D:$D,A35,$B:$B,"Sous-tâche")=0,"To Do",IF(COUNTIFS($D:$D,A35,$B:$B,"Sous-tâche",$Q:$Q,"Done")=COUNTIFS($D:$D,A35,$B:$B,"Sous-tâche"),"Done",IF(COUNTIFS($D:$D,A35,$B:$B,"Sous-tâche",$Q:$Q,"To Do")=COUNTIFS($D:$D,A35,$B:$B,"Sous-tâche"),"To Do","In Progress"))) -> In Progress | R35: L1 – Socle technique / Tâche 1
A36: US-04 | B36: Story | C36: Lot 1 | D36: E03 | E36: E03 | F36: Modèle de données partagé | G36: En tant qu'équipe IT SIVO, je veux un modèle de données documenté avec ses propriétaires, afin de savoir qui écrit et qui lit chaque table. Critères d'acceptation : • MCD/MLD couvrant opticiens, produits, commandes, lignes, statuts, livraisons, réclamations. • Chaque table a un propriétaire (Projet / SIVO) et un mode d'accès (R / RW) validés en atelier. • Le dictionnaire de données est publié et versionné. | H36: Back | I36: Back | J36: Ahmed Jmal | K36: =SUMIFS($K:$K,$E:$E,A36,$B:$B,"Sous-tâche") -> 6 | L36: 13 | M36: Highest | N36: S01 | O36: Devis | P36: Accès réseau / base SIVO | Q36: =IF(COUNTIFS($E:$E,A36,$B:$B,"Sous-tâche")=0,"To Do",IF(COUNTIFS($E:$E,A36,$B:$B,"Sous-tâche",$Q:$Q,"Done")=COUNTIFS($E:$E,A36,$B:$B,"Sous-tâche"),"Done",IF(COUNTIFS($E:$E,A36,$B:$B,"Sous-tâche",$Q:$Q,"To Do")=COUNTIFS($E:$E,A36,$B:$B,"Sous-tâche"),"To Do","In Progress"))) -> In Progress | R36: L1 – Socle technique / Tâche 1
A37: US-04-T1 | B37: Sous-tâche | C37: Lot 1 | D37: E03 | E37: US-04 | F37: [Back] Conception MCD / MLD et conventions de nommage | H37: Back | I37: Back | J37: Ahmed Jmal | K37: 3 | M37: Highest | N37: S01 | O37: Devis | Q37: In Progress | R37: L1 – Socle technique / Tâche 1 | S37: OPT-101, OPT-201..203 | T37: Modèle auth / opticien / vendeur / site / planning en place ; commandes, précal, réclamations à modéliser et à valider avec l'IT SIVO.
A38: US-04-T2 | B38: Sous-tâche | C38: Lot 1 | D38: E03 | E38: US-04 | F38: [Back] Dictionnaire de données + matrice de responsabilités | H38: Back | I38: Back | J38: Ahmed Jmal | K38: 1 | M38: Highest | N38: S01 | O38: Devis | Q38: To Do | R38: L1 – Socle technique / Tâche 1
A39: US-04-T3 | B39: Sous-tâche | C39: Lot 1 | D39: E03 | E39: US-04 | F39: [Back] Mapping ORM des entités et repositories | H39: Back | I39: Back | J39: Ahmed Jmal | K39: 2 | M39: Highest | N39: S01 | O39: Devis | Q39: In Progress | R39: L1 – Socle technique / Tâche 1 | S39: OPT-101 | T39: Prisma 7 pour les entités existantes.
A40: US-05 | B40: Story | C40: Lot 1 | D40: E03 | E40: E03 | F40: Connexion sécurisée au SI SIVO (Oracle) | G40: En tant qu'équipe IT SIVO, je veux que l'application accède à nos données via des comptes de service à droits minimaux, afin de garder le contrôle de notre SI. Critères d'acceptation : • Connexion chiffrée (TLS) avec un compte de service par environnement. • Les droits sont limités aux tables listées dans la matrice US-04. • La synchronisation du catalogue SIVO tourne et ses erreurs sont journalisées. | H40: Back, DevOps | I40: Back, DevOps | J40: Ahmed Jmal | K40: =SUMIFS($K:$K,$E:$E,A40,$B:$B,"Sous-tâche") -> 6 | L40: 13 | M40: Highest | N40: S02 | O40: Devis | P40: Accès réseau / base SIVO | Q40: =IF(COUNTIFS($E:$E,A40,$B:$B,"Sous-tâche")=0,"To Do",IF(COUNTIFS($E:$E,A40,$B:$B,"Sous-tâche",$Q:$Q,"Done")=COUNTIFS($E:$E,A40,$B:$B,"Sous-tâche"),"Done",IF(COUNTIFS($E:$E,A40,$B:$B,"Sous-tâche",$Q:$Q,"To Do")=COUNTIFS($E:$E,A40,$B:$B,"Sous-tâche"),"To Do","In Progress"))) -> In Progress | R40: L1 – Socle technique / Tâche 1
A41: US-05-T1 | B41: Sous-tâche | C41: Lot 1 | D41: E03 | E41: US-05 | F41: [DevOps] Comptes de service, droits, ouverture réseau avec IT SIVO | H41: DevOps | I41: DevOps | J41: Heni Kenoun | K41: 2 | M41: Highest | N41: S02 | O41: Devis | Q41: In Progress | R41: L1 – Socle technique / Tâche 1 | S41: OPT-101 | T41: Rôle PostgreSQL applicatif non-superuser en dev (fait par le Back) ; comptes de service SIVO / Oracle non faits.
A42: US-05-T2 | B42: Sous-tâche | C42: Lot 1 | D42: E03 | E42: US-05 | F42: [Back] Connecteur SIVO + pool de connexions + gestion des erreurs | H42: Back | I42: Back | J42: Ahmed Jmal | K42: 2 | M42: Highest | N42: S02 | O42: Devis | Q42: To Do | R42: L1 – Socle technique / Tâche 1
A43: US-05-T3 | B43: Sous-tâche | C43: Lot 1 | D43: E03 | E43: US-05 | F43: [Back] Synchronisation catalogue / référentiels depuis Oracle SIVO | H43: Back | I43: Back | J43: Ahmed Jmal | K43: 2 | M43: Highest | N43: S02 | O43: Devis | Q43: To Do | R43: L1 – Socle technique / Tâche 1
A44: US-06 | B44: Story | C44: Lot 1 | D44: E03 | E44: E03 | F44: Migrations et jeux de données | G44: En tant que développeur, je veux des migrations versionnées et des données de recette, afin de recréer chaque environnement à l'identique. Critères d'acceptation : • Une migration s'applique et se rejoue (rollback) sans perte sur Dev et Recette. • Un jeu de données anonymisé permet de dérouler tous les parcours Lot 1. | H44: Back | I44: Back | J44: Ahmed Jmal | K44: =SUMIFS($K:$K,$E:$E,A44,$B:$B,"Sous-tâche") -> 3 | L44: 5 | M44: High | N44: S02 | O44: Devis | P44: Accès réseau / base SIVO | Q44: =IF(COUNTIFS($E:$E,A44,$B:$B,"Sous-tâche")=0,"To Do",IF(COUNTIFS($E:$E,A44,$B:$B,"Sous-tâche",$Q:$Q,"Done")=COUNTIFS($E:$E,A44,$B:$B,"Sous-tâche"),"Done",IF(COUNTIFS($E:$E,A44,$B:$B,"Sous-tâche",$Q:$Q,"To Do")=COUNTIFS($E:$E,A44,$B:$B,"Sous-tâche"),"To Do","In Progress"))) -> In Progress | R44: L1 – Socle technique / Tâche 1
A45: US-06-T1 | B45: Sous-tâche | C45: Lot 1 | D45: E03 | E45: US-06 | F45: [Back] Scripts de migration versionnés (up / down) | H45: Back | I45: Back | J45: Ahmed Jmal | K45: 1.5 | M45: High | N45: S02 | O45: Devis | Q45: Done | R45: L1 – Socle technique / Tâche 1 | S45: OPT-101 | T45: Migrations Prisma versionnées et reproductibles.
A46: US-06-T2 | B46: Sous-tâche | C46: Lot 1 | D46: E03 | E46: US-06 | F46: [Back] Jeu de données de recette anonymisé | H46: Back | I46: Back | J46: Ahmed Jmal | K46: 1.5 | M46: High | N46: S02 | O46: Devis | Q46: To Do | R46: L1 – Socle technique / Tâche 1
A47: US-07 | B47: Story | C47: Lot 1 | D47: E03 | E47: E03 | F47: Tests d'intégration SIVO | G47: En tant que PO, je veux des tests d'intégration automatiques avec le SI SIVO, afin de détecter toute rupture avant la mise en production. Critères d'acceptation : • Les flux lecture catalogue / écriture commande sont couverts par des tests automatisés. • Les tests tournent dans la CI et bloquent le déploiement en cas d'échec. | H47: Back | I47: Back | J47: Ahmed Jmal | K47: =SUMIFS($K:$K,$E:$E,A47,$B:$B,"Sous-tâche") -> 3 | L47: 5 | M47: High | N47: S04 | O47: Devis | P47: Accès réseau / base SIVO | Q47: =IF(COUNTIFS($E:$E,A47,$B:$B,"Sous-tâche")=0,"To Do",IF(COUNTIFS($E:$E,A47,$B:$B,"Sous-tâche",$Q:$Q,"Done")=COUNTIFS($E:$E,A47,$B:$B,"Sous-tâche"),"Done",IF(COUNTIFS($E:$E,A47,$B:$B,"Sous-tâche",$Q:$Q,"To Do")=COUNTIFS($E:$E,A47,$B:$B,"Sous-tâche"),"To Do","In Progress"))) -> To Do | R47: L1 – Socle technique / Tâche 1
A48: US-07-T1 | B48: Sous-tâche | C48: Lot 1 | D48: E03 | E48: US-07 | F48: [Back] Tests d'intégration des flux SIVO | H48: Back | I48: Back | J48: Ahmed Jmal | K48: 2 | M48: High | N48: S04 | O48: Devis | Q48: To Do | R48: L1 – Socle technique / Tâche 1
A49: US-07-T2 | B49: Sous-tâche | C49: Lot 1 | D49: E03 | E49: US-07 | F49: [Back] Validation volumétrie et temps de réponse des requêtes | H49: Back | I49: Back | J49: Ahmed Jmal | K49: 1 | M49: High | N49: S04 | O49: Devis | Q49: To Do | R49: L1 – Socle technique / Tâche 1
A50: E04 | B50: Epic | C50: Lot 1 | D50: E04 | F50: Sécurité applicative & protection des données | G50: Objectif : Protéger l'application, les échanges, les secrets et les données sensibles. Réf. : L1 – Socle technique / Tâche 1 | K50: =SUMIFS($K:$K,$D:$D,A50,$B:$B,"Sous-tâche") -> 8.5 | L50: =SUMIFS($L:$L,$D:$D,A50,$B:$B,"Story") -> 16 | M50: High | P50: E01, E02, E03 | Q50: =IF(COUNTIFS($D:$D,A50,$B:$B,"Sous-tâche")=0,"To Do",IF(COUNTIFS($D:$D,A50,$B:$B,"Sous-tâche",$Q:$Q,"Done")=COUNTIFS($D:$D,A50,$B:$B,"Sous-tâche"),"Done",IF(COUNTIFS($D:$D,A50,$B:$B,"Sous-tâche",$Q:$Q,"To Do")=COUNTIFS($D:$D,A50,$B:$B,"Sous-tâche"),"To Do","In Progress"))) -> In Progress | R50: L1 – Socle technique / Tâche 1
A51: US-08 | B51: Story | C51: Lot 1 | D51: E04 | E51: E04 | F51: Sécuriser les échanges, secrets et données sensibles | G51: En tant que responsable sécurité SIVO, je veux que les secrets et données sensibles soient protégés, afin de respecter notre politique de sécurité. Critères d'acceptation : • Aucun secret dans le code ni dans les logs (scan automatique dans la CI). • HTTPS forcé, en-têtes de sécurité (HSTS, CSP) présents. • Les données sensibles identifiées sont chiffrées au repos. | H51: Back, DevOps | I51: Back, DevOps | J51: Ahmed Jmal | K51: =SUMIFS($K:$K,$E:$E,A51,$B:$B,"Sous-tâche") -> 4.5 | L51: 8 | M51: High | N51: S02 | O51: Devis | P51: E01, E02, E03 | Q51: =IF(COUNTIFS($E:$E,A51,$B:$B,"Sous-tâche")=0,"To Do",IF(COUNTIFS($E:$E,A51,$B:$B,"Sous-tâche",$Q:$Q,"Done")=COUNTIFS($E:$E,A51,$B:$B,"Sous-tâche"),"Done",IF(COUNTIFS($E:$E,A51,$B:$B,"Sous-tâche",$Q:$Q,"To Do")=COUNTIFS($E:$E,A51,$B:$B,"Sous-tâche"),"To Do","In Progress"))) -> In Progress | R51: L1 – Socle technique / Tâche 1
A52: US-08-T1 | B52: Sous-tâche | C52: Lot 1 | D52: E04 | E52: US-08 | F52: [DevOps] TLS + coffre à secrets (Vault / équivalent) par environnement | H52: DevOps | I52: DevOps | J52: Heni Kenoun | K52: 1.5 | M52: High | N52: S02 | O52: Devis | Q52: To Do | R52: L1 – Socle technique / Tâche 1
A53: US-08-T2 | B53: Sous-tâche | C53: Lot 1 | D53: E04 | E53: US-08 | F53: [Back] Chiffrement des données sensibles au repos | H53: Back | I53: Back | J53: Ahmed Jmal | K53: 1 | M53: High | N53: S02 | O53: Devis | Q53: To Do | R53: L1 – Socle technique / Tâche 1
A54: US-08-T3 | B54: Sous-tâche | C54: Lot 1 | D54: E04 | E54: US-08 | F54: [Back] Validation des entrées, CORS, en-têtes de sécurité | H54: Back | I54: Back | J54: Ahmed Jmal | K54: 1.5 | M54: High | N54: S02 | O54: Devis | Q54: In Progress | R54: L1 – Socle technique / Tâche 1 | S54: OPT-101, OPT-301 | T54: Validation Zod des variables d'env + DTO ; CORS / en-têtes de sécurité non mentionnés.
A55: US-09 | B55: Story | C55: Lot 1 | D55: E04 | E55: E04 | F55: Journalisation d'audit et protections applicatives | G55: En tant qu'administrateur SIVO, je veux tracer les actions sensibles, afin de pouvoir enquêter en cas d'incident. Critères d'acceptation : • Connexions, échecs de connexion, créations/annulations de commande sont journalisés (qui, quoi, quand). • Après 5 échecs de connexion, le compte est temporisé. • Les logs d'audit ne sont pas modifiables par l'application. | H55: Front Mobile, Back | I55: Front, Back | J55: Ahmed Jmal | K55: =SUMIFS($K:$K,$E:$E,A55,$B:$B,"Sous-tâche") -> 4 | L55: 8 | M55: High | N55: S05 | O55: Devis | P55: E01, E02, E03 | Q55: =IF(COUNTIFS($E:$E,A55,$B:$B,"Sous-tâche")=0,"To Do",IF(COUNTIFS($E:$E,A55,$B:$B,"Sous-tâche",$Q:$Q,"Done")=COUNTIFS($E:$E,A55,$B:$B,"Sous-tâche"),"Done",IF(COUNTIFS($E:$E,A55,$B:$B,"Sous-tâche",$Q:$Q,"To Do")=COUNTIFS($E:$E,A55,$B:$B,"Sous-tâche"),"To Do","In Progress"))) -> In Progress | R55: L1 – Socle technique / Tâche 1
A56: US-09-T1 | B56: Sous-tâche | C56: Lot 1 | D56: E04 | E56: US-09 | F56: [Back] Audit log des actions sensibles | H56: Back | I56: Back | J56: Ahmed Jmal | K56: 1.5 | M56: High | N56: S05 | O56: Devis | Q56: In Progress | R56: L1 – Socle technique / Tâche 1 | S56: OPT-204 | T56: Log d'audit 'vendor_access_denied' seulement ; autres actions sensibles à tracer.
A57: US-09-T2 | B57: Sous-tâche | C57: Lot 1 | D57: E04 | E57: US-09 | F57: [Back] Table d'audit + politique de rétention | H57: Back | I57: Back | J57: Ahmed Jmal | K57: 1 | M57: High | N57: S05 | O57: Devis | Q57: To Do | R57: L1 – Socle technique / Tâche 1
A58: US-09-T3 | B58: Sous-tâche | C58: Lot 1 | D58: E04 | E58: US-09 | F58: [Back] Rate limiting et anti brute-force | H58: Back | I58: Back | J58: Ahmed Jmal | K58: 1 | M58: High | N58: S05 | O58: Devis | Q58: Done | R58: L1 – Socle technique / Tâche 1 | S58: OPT-105 | T58: Double rate limiting + anti-timing. Écart vs critère « temporisation après 5 échecs » → à arbitrer.
A59: US-09-T4 | B59: Sous-tâche | C59: Lot 1 | D59: E04 | E59: US-09 | F59: [Front Mobile] Sécurité mobile : stockage sécurisé du jeton, certificate pinning | H59: Front Mobile | I59: Front | J59: Youssef Feki | K59: 0.5 | M59: High | N59: S05 | O59: Devis | Q59: In Progress | R59: L1 – Socle technique / Tâche 1 | S59: Rapport Front §3C | T59: Keychain / Keystore OK ; certificate pinning non mentionné.
A60: E05 | B60: Epic | C60: Lot 1 | D60: E05 | F60: Environnements, CI/CD & déploiement | G60: Objectif : Disposer d'un processus fiable pour développer, tester et mettre en production. Réf. : L1 – Socle technique / Tâche 2 (DevOps) | K60: =SUMIFS($K:$K,$D:$D,A60,$B:$B,"Sous-tâche") -> 15 | L60: =SUMIFS($L:$L,$D:$D,A60,$B:$B,"Story") -> 26 | M60: Highest | P60: Infrastructure / hébergement SIVO | Q60: =IF(COUNTIFS($D:$D,A60,$B:$B,"Sous-tâche")=0,"To Do",IF(COUNTIFS($D:$D,A60,$B:$B,"Sous-tâche",$Q:$Q,"Done")=COUNTIFS($D:$D,A60,$B:$B,"Sous-tâche"),"Done",IF(COUNTIFS($D:$D,A60,$B:$B,"Sous-tâche",$Q:$Q,"To Do")=COUNTIFS($D:$D,A60,$B:$B,"Sous-tâche"),"To Do","In Progress"))) -> In Progress | R60: L1 – Socle technique / Tâche 2 (DevOps)
A61: US-10 | B61: Story | C61: Lot 1 | D61: E05 | E61: E05 | F61: Environnements Dev / Recette / Production | G61: En tant qu'équipe projet, je veux trois environnements isolés, afin de développer et faire valider sans risque pour la production. Critères d'acceptation : • Dev, Recette et Prod sont provisionnés, isolés et accessibles selon les règles SIVO. • La configuration est externalisée (aucune valeur d'environnement dans le code). | H61: DevOps | I61: DevOps | J61: Heni Kenoun | K61: =SUMIFS($K:$K,$E:$E,A61,$B:$B,"Sous-tâche") -> 7 | L61: 13 | M61: Highest | N61: S01 | O61: Devis | P61: Infrastructure / hébergement SIVO | Q61: =IF(COUNTIFS($E:$E,A61,$B:$B,"Sous-tâche")=0,"To Do",IF(COUNTIFS($E:$E,A61,$B:$B,"Sous-tâche",$Q:$Q,"Done")=COUNTIFS($E:$E,A61,$B:$B,"Sous-tâche"),"Done",IF(COUNTIFS($E:$E,A61,$B:$B,"Sous-tâche",$Q:$Q,"To Do")=COUNTIFS($E:$E,A61,$B:$B,"Sous-tâche"),"To Do","In Progress"))) -> In Progress | R61: L1 – Socle technique / Tâche 2 (DevOps)
A62: US-10-T1 | B62: Sous-tâche | C62: Lot 1 | D62: E05 | E62: US-10 | F62: [DevOps] Provisionnement infrastructure des 3 environnements | H62: DevOps | I62: DevOps | J62: Heni Kenoun | K62: 3 | M62: Highest | N62: S01 | O62: Devis | Q62: To Do | R62: L1 – Socle technique / Tâche 2 (DevOps)
A63: US-10-T2 | B63: Sous-tâche | C63: Lot 1 | D63: E05 | E63: US-10 | F63: [DevOps] Conteneurisation (Docker) front / back / IA | H63: DevOps | I63: DevOps | J63: Heni Kenoun | K63: 2 | M63: Highest | N63: S01 | O63: Devis | Q63: In Progress | R63: L1 – Socle technique / Tâche 2 (DevOps) | S63: OPT-101 | T63: Docker Compose de dev (PostgreSQL 17, MinIO, Mailpit) fait par le Back ; images front / back / IA et environnements Recette / Prod à faire (DevOps).
A64: US-10-T3 | B64: Sous-tâche | C64: Lot 1 | D64: E05 | E64: US-10 | F64: [DevOps] Configuration par environnement et gestion des variables | H64: DevOps | I64: DevOps | J64: Heni Kenoun | K64: 2 | M64: Highest | N64: S01 | O64: Devis | Q64: To Do | R64: L1 – Socle technique / Tâche 2 (DevOps)
A65: US-11 | B65: Story | C65: Lot 1 | D65: E05 | E65: E05 | F65: Pipeline CI/CD avec retour arrière | G65: En tant qu'équipe projet, je veux un pipeline automatisé, afin de livrer souvent et revenir en arrière en cas de problème. Critères d'acceptation : • Chaque merge sur la branche principale déclenche build + tests + déploiement Recette. • La mise en production nécessite une validation manuelle. • Un rollback vers la version N-1 se fait en < 15 min. | H65: Front Mobile, Back, DevOps | I65: Front, Back, DevOps | J65: Heni Kenoun | K65: =SUMIFS($K:$K,$E:$E,A65,$B:$B,"Sous-tâche") -> 8 | L65: 13 | M65: High | N65: S03 | O65: Devis | P65: Infrastructure / hébergement SIVO | Q65: =IF(COUNTIFS($E:$E,A65,$B:$B,"Sous-tâche")=0,"To Do",IF(COUNTIFS($E:$E,A65,$B:$B,"Sous-tâche",$Q:$Q,"Done")=COUNTIFS($E:$E,A65,$B:$B,"Sous-tâche"),"Done",IF(COUNTIFS($E:$E,A65,$B:$B,"Sous-tâche",$Q:$Q,"To Do")=COUNTIFS($E:$E,A65,$B:$B,"Sous-tâche"),"To Do","In Progress"))) -> To Do | R65: L1 – Socle technique / Tâche 2 (DevOps)
A66: US-11-T1 | B66: Sous-tâche | C66: Lot 1 | D66: E05 | E66: US-11 | F66: [DevOps] Pipeline build + tests + analyse qualité | H66: DevOps | I66: DevOps | J66: Heni Kenoun | K66: 3 | M66: High | N66: S03 | O66: Devis | Q66: To Do | R66: L1 – Socle technique / Tâche 2 (DevOps)
A67: US-11-T2 | B67: Sous-tâche | C67: Lot 1 | D67: E05 | E67: US-11 | F67: [DevOps] Déploiement automatisé + procédure de rollback | H67: DevOps | I67: DevOps | J67: Heni Kenoun | K67: 3 | M67: High | N67: S03 | O67: Devis | Q67: To Do | R67: L1 – Socle technique / Tâche 2 (DevOps)
A68: US-11-T3 | B68: Sous-tâche | C68: Lot 1 | D68: E05 | E68: US-11 | F68: [Front Mobile] Intégration des builds mobile (iOS / Android) dans le pipeline | H68: Front Mobile | I68: Front | J68: Youssef Feki | K68: 1 | M68: High | N68: S03 | O68: Devis | Q68: To Do | R68: L1 – Socle technique / Tâche 2 (DevOps)
A69: US-11-T4 | B69: Sous-tâche | C69: Lot 1 | D69: E05 | E69: US-11 | F69: [Back] Intégration des tests back dans le pipeline | H69: Back | I69: Back | J69: Ahmed Jmal | K69: 1 | M69: High | N69: S03 | O69: Devis | Q69: To Do | R69: L1 – Socle technique / Tâche 2 (DevOps)
A70: E18 | B70: Epic | C70: Lot 1 | D70: E18 | F70: Module vendeurs & gestion des accès | G70: Objectif : Permettre à l'opticien de créer ses vendeurs et de contrôler à quels sites et à quelles heures ils accèdent. Réf. : Hors devis — ajout Lot 1 (avenant) | K70: =SUMIFS($K:$K,$D:$D,A70,$B:$B,"Sous-tâche") -> 24 | L70: =SUMIFS($L:$L,$D:$D,A70,$B:$B,"Story") -> 39 | M70: Highest | P70: E01, E02 | Q70: =IF(COUNTIFS($D:$D,A70,$B:$B,"Sous-tâche")=0,"To Do",IF(COUNTIFS($D:$D,A70,$B:$B,"Sous-tâche",$Q:$Q,"Done")=COUNTIFS($D:$D,A70,$B:$B,"Sous-tâche"),"Done",IF(COUNTIFS($D:$D,A70,$B:$B,"Sous-tâche",$Q:$Q,"To Do")=COUNTIFS($D:$D,A70,$B:$B,"Sous-tâche"),"To Do","In Progress"))) -> In Progress | R70: Hors devis — ajout Lot 1 (avenant)
A71: US-51 | B71: Story | C71: Lot 1 | D71: E18 | E71: E18 | F71: Configuration du compte opticien et de ses sites | G71: En tant qu'opticien, je veux configurer mon compte et déclarer mes sites (magasins), afin d'y rattacher mes vendeurs. Critères d'acceptation : • Je gère les informations de mon compte et la liste de mes sites (création, modification, désactivation). • Un site désactivé n'est plus sélectionnable pour une commande ni un rattachement. • Le fuseau horaire du site est enregistré (utilisé pour les plages d'accès). | H71: Front Mobile, Back | I71: Front, Back | J71: Ahmed Jmal | K71: =SUMIFS($K:$K,$E:$E,A71,$B:$B,"Sous-tâche") -> 3.5 | L71: 8 | M71: Highest | N71: S02 | O71: À valider | P71: E01, E02 | Q71: =IF(COUNTIFS($E:$E,A71,$B:$B,"Sous-tâche")=0,"To Do",IF(COUNTIFS($E:$E,A71,$B:$B,"Sous-tâche",$Q:$Q,"Done")=COUNTIFS($E:$E,A71,$B:$B,"Sous-tâche"),"Done",IF(COUNTIFS($E:$E,A71,$B:$B,"Sous-tâche",$Q:$Q,"To Do")=COUNTIFS($E:$E,A71,$B:$B,"Sous-tâche"),"To Do","In Progress"))) -> In Progress | R71: Hors devis — ajout Lot 1 (avenant)
A72: US-51-T1 | B72: Sous-tâche | C72: Lot 1 | D72: E18 | E72: US-51 | F72: [Back] Modèle compte opticien / sites + API de configuration | H72: Back | I72: Back | J72: Ahmed Jmal | K72: 2 | M72: Highest | N72: S02 | O72: À valider | Q72: In Progress | R72: Hors devis — ajout Lot 1 (avenant) | S72: OPT-202, OPT-203 | T72: Modèle Site (codeSite, libelle, timezone IANA, actif) ; API de configuration du compte et des sites non faite.
A73: US-51-T2 | B73: Sous-tâche | C73: Lot 1 | D73: E18 | E73: US-51 | F73: [Front Mobile] Écrans 'Mon compte' et 'Mes sites' | H73: Front Mobile | I73: Front | J73: Youssef Feki | K73: 1.5 | M73: Highest | N73: S02 | O73: À valider | Q73: To Do | R73: Hors devis — ajout Lot 1 (avenant)
A74: US-52 | B74: Story | C74: Lot 1 | D74: E18 | E74: E18 | F74: Créer et gérer les comptes vendeurs | G74: En tant qu'opticien, je veux créer, modifier et désactiver des comptes vendeurs, afin que mon équipe commande sous son propre identifiant. Critères d'acceptation : • Création avec nom, e-mail / identifiant, rôle vendeur ; le vendeur reçoit une invitation pour définir son mot de passe. • Désactivation immédiate : les sessions en cours du vendeur sont révoquées. • Un opticien ne voit et ne gère que ses propres vendeurs. | H74: Front Mobile, Back | I74: Front, Back | J74: Ahmed Jmal | K74: =SUMIFS($K:$K,$E:$E,A74,$B:$B,"Sous-tâche") -> 6.5 | L74: 8 | M74: Highest | N74: S02 | O74: À valider | P74: E01, E02 | Q74: =IF(COUNTIFS($E:$E,A74,$B:$B,"Sous-tâche")=0,"To Do",IF(COUNTIFS($E:$E,A74,$B:$B,"Sous-tâche",$Q:$Q,"Done")=COUNTIFS($E:$E,A74,$B:$B,"Sous-tâche"),"Done",IF(COUNTIFS($E:$E,A74,$B:$B,"Sous-tâche",$Q:$Q,"To Do")=COUNTIFS($E:$E,A74,$B:$B,"Sous-tâche"),"To Do","In Progress"))) -> In Progress | R74: Hors devis — ajout Lot 1 (avenant)
A75: US-52-T1 | B75: Sous-tâche | C75: Lot 1 | D75: E18 | E75: US-52 | F75: [Back] Modèle vendeur rattaché à l'opticien + API CRUD + invitation | H75: Back | I75: Back | J75: Ahmed Jmal | K75: 2 | M75: Highest | N75: S02 | O75: À valider | Q75: Done | R75: Hors devis — ajout Lot 1 (avenant) | S75: OPT-201, OPT-207 | T75: CRUD vendeurs paginé, recherche, codeVendeur, statuts ACTIVE / INACTIF / TERMINATED sans suppression physique.
A76: US-52-T2 | B76: Sous-tâche | C76: Lot 1 | D76: E18 | E76: US-52 | F76: [Back] Révocation des sessions à la désactivation | H76: Back | I76: Back | J76: Ahmed Jmal | K76: 0.5 | M76: Highest | N76: S02 | O76: À valider | Q76: Done | R76: Hors devis — ajout Lot 1 (avenant) | S76: OPT-201, OPT-204 | T76: Révocation immédiate via contrôle à chaque requête (stateless).
A77: US-52-T3 | B77: Sous-tâche | C77: Lot 1 | D77: E18 | E77: US-52 | F77: [Front Mobile] Écrans liste / création / édition des vendeurs | H77: Front Mobile | I77: Front | J77: Youssef Feki | K77: 2 | M77: Highest | N77: S02 | O77: À valider | Q77: To Do | R77: Hors devis — ajout Lot 1 (avenant)
A78: US-53 | B78: Story | C78: Lot 1 | D78: E18 | E78: E18 | F78: Rattacher un vendeur à un ou plusieurs sites | G78: En tant qu'opticien, je veux choisir les sites auxquels chaque vendeur a accès, afin qu'il ne voie que les commandes de son magasin. Critères d'acceptation : • Un vendeur est rattaché à ≥ 1 site. • Il ne voit et ne crée des commandes que pour ses sites (contrôle côté API). • Retirer un site retire l'accès immédiatement. | H78: Front Mobile, Back | I78: Front, Back | J78: Ahmed Jmal | K78: =SUMIFS($K:$K,$E:$E,A78,$B:$B,"Sous-tâche") -> 3.5 | L78: 5 | M78: Highest | N78: S03 | O78: À valider | P78: E01, E02 | Q78: =IF(COUNTIFS($E:$E,A78,$B:$B,"Sous-tâche")=0,"To Do",IF(COUNTIFS($E:$E,A78,$B:$B,"Sous-tâche",$Q:$Q,"Done")=COUNTIFS($E:$E,A78,$B:$B,"Sous-tâche"),"Done",IF(COUNTIFS($E:$E,A78,$B:$B,"Sous-tâche",$Q:$Q,"To Do")=COUNTIFS($E:$E,A78,$B:$B,"Sous-tâche"),"To Do","In Progress"))) -> In Progress | R78: Hors devis — ajout Lot 1 (avenant)
A79: US-53-T1 | B79: Sous-tâche | C79: Lot 1 | D79: E18 | E79: US-53 | F79: [Back] Table vendeur ↔ sites + filtrage des données par site dans l'API | H79: Back | I79: Back | J79: Ahmed Jmal | K79: 1.5 | M79: Highest | N79: S03 | O79: À valider | Q79: Done | R79: Hors devis — ajout Lot 1 (avenant) | S79: OPT-202 | T79: Affectations multi-sites datées. Filtrage par site à brancher sur les futures API commandes.
A80: US-53-T2 | B80: Sous-tâche | C80: Lot 1 | D80: E18 | E80: US-53 | F80: [Front Mobile] Sélection des sites dans la fiche vendeur | H80: Front Mobile | I80: Front | J80: Youssef Feki | K80: 1 | M80: Highest | N80: S03 | O80: À valider | Q80: To Do | R80: Hors devis — ajout Lot 1 (avenant)
A81: US-54 | B81: Story | C81: Lot 1 | D81: E18 | E81: E18 | F81: Plages d'accès : jours et heures | G81: En tant qu'opticien, je veux définir les jours et heures où chaque vendeur peut se connecter, afin de limiter l'accès aux heures d'ouverture. Critères d'acceptation : • Plages configurables par jour (ex. lun–sam 09:00–19:00), selon le fuseau du site. • Hors plage : connexion refusée avec message explicite ; une session ouverte expire à la fin de la plage. • L'opticien (compte principal) n'est jamais limité. | H81: Front Mobile, Back | I81: Front, Back | J81: Ahmed Jmal | K81: =SUMIFS($K:$K,$E:$E,A81,$B:$B,"Sous-tâche") -> 4.5 | L81: 8 | M81: Highest | N81: S03 | O81: À valider | P81: E01, E02 | Q81: =IF(COUNTIFS($E:$E,A81,$B:$B,"Sous-tâche")=0,"To Do",IF(COUNTIFS($E:$E,A81,$B:$B,"Sous-tâche",$Q:$Q,"Done")=COUNTIFS($E:$E,A81,$B:$B,"Sous-tâche"),"Done",IF(COUNTIFS($E:$E,A81,$B:$B,"Sous-tâche",$Q:$Q,"To Do")=COUNTIFS($E:$E,A81,$B:$B,"Sous-tâche"),"To Do","In Progress"))) -> In Progress | R81: Hors devis — ajout Lot 1 (avenant)
A82: US-54-T1 | B82: Sous-tâche | C82: Lot 1 | D82: E18 | E82: US-54 | F82: [Back] Modèle des plages + contrôle au login et à chaque requête (middleware) | H82: Back | I82: Back | J82: Ahmed Jmal | K82: 2.5 | M82: Highest | N82: S03 | O82: À valider | Q82: Done | R82: Hors devis — ajout Lot 1 (avenant) | S82: OPT-203, OPT-204 | T82: Planning ISO 7 jours par affectation + VendorAccessPolicy fail-closed au login, au refresh et à chaque requête.
A83: US-54-T2 | B83: Sous-tâche | C83: Lot 1 | D83: E18 | E83: US-54 | F83: [Back] Expiration des sessions en fin de plage + gestion des fuseaux | H83: Back | I83: Back | J83: Ahmed Jmal | K83: 0.5 | M83: Highest | N83: S03 | O83: À valider | Q83: Done | R83: Hors devis — ajout Lot 1 (avenant) | S83: OPT-203 | T83: Fuseau IANA par site validé en base et en applicatif.
A84: US-54-T3 | B84: Sous-tâche | C84: Lot 1 | D84: E18 | E84: US-54 | F84: [Front Mobile] Écran de configuration des jours et heures | H84: Front Mobile | I84: Front | J84: Youssef Feki | K84: 1.5 | M84: Highest | N84: S03 | O84: À valider | Q84: To Do | R84: Hors devis — ajout Lot 1 (avenant)
A85: US-55 | B85: Story | C85: Lot 1 | D85: E18 | E85: E18 | F85: Permissions vendeur et traçabilité | G85: En tant qu'opticien, je veux définir ce que mes vendeurs peuvent faire et savoir qui a passé chaque commande, afin de garder le contrôle. Critères d'acceptation : • Permissions configurables (ex. commander, voir les prix, déclarer une réclamation). • Chaque commande / réclamation enregistre le vendeur auteur. • Tests automatisés : vendeur hors site, hors plage, désactivé → accès refusé. | H85: Front Mobile, Back | I85: Front, Back | J85: Ahmed Jmal | K85: =SUMIFS($K:$K,$E:$E,A85,$B:$B,"Sous-tâche") -> 3 | L85: 5 | M85: High | N85: S07 | O85: À valider | P85: E01, E02 | Q85: =IF(COUNTIFS($E:$E,A85,$B:$B,"Sous-tâche")=0,"To Do",IF(COUNTIFS($E:$E,A85,$B:$B,"Sous-tâche",$Q:$Q,"Done")=COUNTIFS($E:$E,A85,$B:$B,"Sous-tâche"),"Done",IF(COUNTIFS($E:$E,A85,$B:$B,"Sous-tâche",$Q:$Q,"To Do")=COUNTIFS($E:$E,A85,$B:$B,"Sous-tâche"),"To Do","In Progress"))) -> In Progress | R85: Hors devis — ajout Lot 1 (avenant)
A86: US-55-T1 | B86: Sous-tâche | C86: Lot 1 | D86: E18 | E86: US-55 | F86: [Back] Permissions vendeur + auteur sur commandes / réclamations | H86: Back | I86: Back | J86: Ahmed Jmal | K86: 1.5 | M86: High | N86: S07 | O86: À valider | Q86: To Do | R86: Hors devis — ajout Lot 1 (avenant)
A87: US-55-T2 | B87: Sous-tâche | C87: Lot 1 | D87: E18 | E87: US-55 | F87: [Back] Tests automatisés du module vendeurs | H87: Back | I87: Back | J87: Ahmed Jmal | K87: 1 | M87: High | N87: S07 | O87: À valider | Q87: Done | R87: Hors devis — ajout Lot 1 (avenant) | S87: OPT-302 | T87: Cas limites horaires testés (07:59:59 refusé, 08:00 accepté, 18:00 refusé).
A88: US-55-T3 | B88: Sous-tâche | C88: Lot 1 | D88: E18 | E88: US-55 | F88: [Front Mobile] Écran des permissions du vendeur | H88: Front Mobile | I88: Front | J88: Youssef Feki | K88: 0.5 | M88: High | N88: S07 | O88: À valider | Q88: To Do | R88: Hors devis — ajout Lot 1 (avenant)
A89: US-W03 | B89: Story | C89: Lot 1 | D89: E18 | E89: E18 | F89: Version web — Module vendeurs & gestion des accès | G89: En tant qu'utilisateur web, je veux retrouver sur navigateur les fonctions « Module vendeurs & gestion des accès » de l'application mobile, afin de travailler depuis mon poste. Critères d'acceptation : • Mêmes règles et mêmes API que la version mobile (aucune logique métier dupliquée). • Affichage correct sur Chrome, Edge, Safari, Firefox (2 dernières versions), de 1280 px à la tablette. • Critères d'acceptation des stories mobiles de l'épic re-vérifiés sur le web. | H89: Front Web | I89: Front | J89: Youssef Feki | K89: =SUMIFS($K:$K,$E:$E,A89,$B:$B,"Sous-tâche") -> 3 | L89: 5 | M89: Highest | N89: S09 | O89: À valider | P89: E01, E02 | Q89: =IF(COUNTIFS($E:$E,A89,$B:$B,"Sous-tâche")=0,"To Do",IF(COUNTIFS($E:$E,A89,$B:$B,"Sous-tâche",$Q:$Q,"Done")=COUNTIFS($E:$E,A89,$B:$B,"Sous-tâche"),"Done",IF(COUNTIFS($E:$E,A89,$B:$B,"Sous-tâche",$Q:$Q,"To Do")=COUNTIFS($E:$E,A89,$B:$B,"Sous-tâche"),"To Do","In Progress"))) -> To Do | R89: Hors devis — ajout Lot 1 (avenant)
A90: US-W03-T1 | B90: Sous-tâche | C90: Lot 1 | D90: E18 | E90: US-W03 | F90: [Front Web] Compte, sites, vendeurs, plages d'accès (web) | H90: Front Web | I90: Front | J90: Youssef Feki | K90: 3 | M90: Highest | N90: S09 | O90: À valider | Q90: To Do | R90: Hors devis — ajout Lot 1 (avenant)
A91: E06 | B91: Epic | C91: Lot 1 | D91: E06 | F91: Passation de commandes standard (Stock, RX) | G91: Objectif : Permettre à l'opticien de rechercher un produit et de créer une commande Stock ou RX. Réf. : L1 – Fonctionnel métier / Tâche 1 | K91: =SUMIFS($K:$K,$D:$D,A91,$B:$B,"Sous-tâche") -> 33.5 | L91: =SUMIFS($L:$L,$D:$D,A91,$B:$B,"Story") -> 65 | M91: Highest | P91: E01, E02, E03 | Q91: =IF(COUNTIFS($D:$D,A91,$B:$B,"Sous-tâche")=0,"To Do",IF(COUNTIFS($D:$D,A91,$B:$B,"Sous-tâche",$Q:$Q,"Done")=COUNTIFS($D:$D,A91,$B:$B,"Sous-tâche"),"Done",IF(COUNTIFS($D:$D,A91,$B:$B,"Sous-tâche",$Q:$Q,"To Do")=COUNTIFS($D:$D,A91,$B:$B,"Sous-tâche"),"To Do","In Progress"))) -> To Do | R91: L1 – Fonctionnel métier / Tâche 1
A92: US-12 | B92: Story | C92: Lot 1 | D92: E06 | E92: E06 | F92: Catalogue et recherche produits | G92: En tant qu'opticien, je veux rechercher et filtrer le catalogue SIVO, afin de trouver rapidement le produit à commander. Critères d'acceptation : • Recherche par référence, libellé, marque ; filtres (type, indice, traitement, disponibilité). • Résultats paginés, réponse < 1 s sur le volume catalogue réel. • Recherche sans résultat : message + suggestion de vider les filtres. • Périmètre agence / stock à valider avant le sprint (point ouvert devis). | H92: Front Mobile, Back | I92: Front, Back | J92: Ahmed Jmal | K92: =SUMIFS($K:$K,$E:$E,A92,$B:$B,"Sous-tâche") -> 8 | L92: 13 | M92: Highest | N92: S03 | O92: Devis | P92: E01, E02, E03 | Q92: =IF(COUNTIFS($E:$E,A92,$B:$B,"Sous-tâche")=0,"To Do",IF(COUNTIFS($E:$E,A92,$B:$B,"Sous-tâche",$Q:$Q,"Done")=COUNTIFS($E:$E,A92,$B:$B,"Sous-tâche"),"Done",IF(COUNTIFS($E:$E,A92,$B:$B,"Sous-tâche",$Q:$Q,"To Do")=COUNTIFS($E:$E,A92,$B:$B,"Sous-tâche"),"To Do","In Progress"))) -> To Do | R92: L1 – Fonctionnel métier / Tâche 1
A93: US-12-T1 | B93: Sous-tâche | C93: Lot 1 | D93: E06 | E93: US-12 | F93: [Back] Index et vues de recherche catalogue | H93: Back | I93: Back | J93: Ahmed Jmal | K93: 1.5 | M93: Highest | N93: S03 | O93: Devis | Q93: To Do | R93: L1 – Fonctionnel métier / Tâche 1
A94: US-12-T2 | B94: Sous-tâche | C94: Lot 1 | D94: E06 | E94: US-12 | F94: [Back] API catalogue : recherche, filtres, pagination | H94: Back | I94: Back | J94: Ahmed Jmal | K94: 3 | M94: Highest | N94: S03 | O94: Devis | Q94: To Do | R94: L1 – Fonctionnel métier / Tâche 1
A95: US-12-T3 | B95: Sous-tâche | C95: Lot 1 | D95: E06 | E95: US-12 | F95: [Front Mobile] Écran catalogue + recherche + filtres | H95: Front Mobile | I95: Front | J95: Youssef Feki | K95: 3.5 | M95: Highest | N95: S03 | O95: Devis | Q95: To Do | R95: L1 – Fonctionnel métier / Tâche 1
A96: US-13 | B96: Story | C96: Lot 1 | D96: E06 | E96: E06 | F96: Commande Stock (panier) | G96: En tant qu'opticien, je veux ajouter des produits stock à un panier et valider ma commande, afin de me réapprovisionner. Critères d'acceptation : • Je peux ajouter, modifier la quantité, supprimer une ligne. • Un produit indisponible ne peut pas être validé (message explicite). • Le récapitulatif affiche références, quantités et référence de commande avant validation. | H96: Front Mobile, Back | I96: Front, Back | J96: Ahmed Jmal | K96: =SUMIFS($K:$K,$E:$E,A96,$B:$B,"Sous-tâche") -> 6 | L96: 13 | M96: Highest | N96: S03 | O96: Devis | P96: E01, E02, E03 | Q96: =IF(COUNTIFS($E:$E,A96,$B:$B,"Sous-tâche")=0,"To Do",IF(COUNTIFS($E:$E,A96,$B:$B,"Sous-tâche",$Q:$Q,"Done")=COUNTIFS($E:$E,A96,$B:$B,"Sous-tâche"),"Done",IF(COUNTIFS($E:$E,A96,$B:$B,"Sous-tâche",$Q:$Q,"To Do")=COUNTIFS($E:$E,A96,$B:$B,"Sous-tâche"),"To Do","In Progress"))) -> To Do | R96: L1 – Fonctionnel métier / Tâche 1
A97: US-13-T1 | B97: Sous-tâche | C97: Lot 1 | D97: E06 | E97: US-13 | F97: [Back] Tables commandes / lignes de commande | H97: Back | I97: Back | J97: Ahmed Jmal | K97: 1 | M97: Highest | N97: S03 | O97: Devis | Q97: To Do | R97: L1 – Fonctionnel métier / Tâche 1
A98: US-13-T2 | B98: Sous-tâche | C98: Lot 1 | D98: E06 | E98: US-13 | F98: [Back] API panier + règles de validation commande Stock | H98: Back | I98: Back | J98: Ahmed Jmal | K98: 2.5 | M98: Highest | N98: S03 | O98: Devis | Q98: To Do | R98: L1 – Fonctionnel métier / Tâche 1
A99: US-13-T3 | B99: Sous-tâche | C99: Lot 1 | D99: E06 | E99: US-13 | F99: [Front Mobile] Panier et récapitulatif de commande | H99: Front Mobile | I99: Front | J99: Youssef Feki | K99: 2.5 | M99: Highest | N99: S03 | O99: Devis | Q99: To Do | R99: L1 – Fonctionnel métier / Tâche 1
A100: US-14 | B100: Story | C100: Lot 1 | D100: E06 | E100: E06 | F100: Commande RX (verres sur prescription) | G100: En tant qu'opticien, je veux saisir une prescription et commander des verres RX, afin de répondre à l'ordonnance de mon client. Critères d'acceptation : • Saisie OD/OG : sphère, cylindre, axe, addition, écarts pupillaires, hauteur. • Les valeurs hors plage fabricable sont bloquées avec un message champ par champ. • Seuls les verres compatibles avec la prescription sont proposés. • Je peux enregistrer un brouillon et le reprendre. | H100: Front Mobile, Back | I100: Front, Back | J100: Ahmed Jmal | K100: =SUMIFS($K:$K,$E:$E,A100,$B:$B,"Sous-tâche") -> 7 | L100: 13 | M100: Highest | N100: S04 | O100: Devis | P100: E01, E02, E03 | Q100: =IF(COUNTIFS($E:$E,A100,$B:$B,"Sous-tâche")=0,"To Do",IF(COUNTIFS($E:$E,A100,$B:$B,"Sous-tâche",$Q:$Q,"Done")=COUNTIFS($E:$E,A100,$B:$B,"Sous-tâche"),"Done",IF(COUNTIFS($E:$E,A100,$B:$B,"Sous-tâche",$Q:$Q,"To Do")=COUNTIFS($E:$E,A100,$B:$B,"Sous-tâche"),"To Do","In Progress"))) -> To Do | R100: L1 – Fonctionnel métier / Tâche 1
...

Sheet Tâches par personne
A1: Vue d'affectation — une section par personne, triée par sprint
A3: Développeur | B3: Rôle | C3: Sprint | D3: Clé | E3: Story | F3: Tâche | G3: J/H | H3: Lot | I3: Source | J3: Priorité
A4: Youssef Feki | B4: Front Mobile | C4: S01 | D4: US-01-T2 | E4: US-01 – Connexion / déconnexion sécurisée | F4: Écran de connexion mobile + gestion du jeton et redirections | G4: 1 | H4: Lot 1 | I4: Devis | J4: Highest
A5: Youssef Feki | B5: Front Mobile | C5: S01 | D5: US-02-T2 | E5: US-02 – Mot de passe oublié & réinitialisation | F5: Écrans mot de passe oublié / nouveau mot de passe | G5: 0.5 | H5: Lot 1 | I5: Devis | J5: High
A6: Youssef Feki | B6: Front Mobile | C6: S01 | D6: US-03-T3 | E6: US-03 – Matrice des rôles et contrôle d'accès | F6: Guards de routes et masquage conditionnel des actions | G6: 0.5 | H6: Lot 1 | I6: Devis | J6: Highest
A7: Youssef Feki | B7: Front Mobile | C7: S01 | D7: US-59-T1 | E7: US-59 – Initialisation de l'application mobile | F7: Initialisation projet, navigation, design system | G7: 3 | H7: Lot 1 | I7: À valider | J7: Highest
A8: Youssef Feki | B8: Front Mobile | C8: S01 | D8: US-59-T2 | E8: US-59 – Initialisation de l'application mobile | F8: Client API typé + gestion des erreurs et du mode hors ligne | G8: 1 | H8: Lot 1 | I8: À valider | J8: Highest
A9: Youssef Feki | B9: Front Mobile | C9: S02 | D9: US-51-T2 | E9: US-51 – Configuration du compte opticien et de ses sites | F9: Écrans 'Mon compte' et 'Mes sites' | G9: 1.5 | H9: Lot 1 | I9: À valider | J9: Highest
A10: Youssef Feki | B10: Front Mobile | C10: S02 | D10: US-52-T3 | E10: US-52 – Créer et gérer les comptes vendeurs | F10: Écrans liste / création / édition des vendeurs | G10: 2 | H10: Lot 1 | I10: À valider | J10: Highest
A11: Youssef Feki | B11: Front Mobile | C11: S03 | D11: US-11-T3 | E11: US-11 – Pipeline CI/CD avec retour arrière | F11: Intégration des builds mobile (iOS / Android) dans le pipeline | G11: 1 | H11: Lot 1 | I11: Devis | J11: High
A12: Youssef Feki | B12: Front Mobile | C12: S03 | D12: US-12-T3 | E12: US-12 – Catalogue et recherche produits | F12: Écran catalogue + recherche + filtres | G12: 3.5 | H12: Lot 1 | I12: Devis | J12: Highest
A13: Youssef Feki | B13: Front Mobile | C13: S03 | D13: US-13-T3 | E13: US-13 – Commande Stock (panier) | F13: Panier et récapitulatif de commande | G13: 2.5 | H13: Lot 1 | I13: Devis | J13: Highest
A14: Youssef Feki | B14: Front Mobile | C14: S03 | D14: US-53-T2 | E14: US-53 – Rattacher un vendeur à un ou plusieurs sites | F14: Sélection des sites dans la fiche vendeur | G14: 1 | H14: Lot 1 | I14: À valider | J14: Highest
A15: Youssef Feki | B15: Front Mobile | C15: S03 | D15: US-54-T3 | E15: US-54 – Plages d'accès : jours et heures | F15: Écran de configuration des jours et heures | G15: 1.5 | H15: Lot 1 | I15: À valider | J15: Highest
... A61: Youssef Feki | B61: Front Web | C61: S12 | D61: US-W12-T1 | E61: US-W12 – Version web — Chatbot IA (suivi, réponse formelle, création depuis formulaire) | F61: Widget de chat (web) | G61: 2 | H61: Lot 3 | I61: À valider | J61: High
F62: Sous-total Youssef Feki | G62: =SUM(G4:G61) -> 102
A64: Ahmed Jmal | B64: Back | C64: S01 | D64: US-01-T1 | E64: US-01 – Connexion / déconnexion sécurisée | F64: API login / logout / refresh token (JWT) + expiration de session | G64: 1.5 | H64: Lot 1 | I64: Devis | J64: Highest
A65: Ahmed Jmal | B65: Back | C65: S01 | D65: US-01-T3 | E65: US-01 – Connexion / déconnexion sécurisée | F65: Tables users / sessions / refresh_tokens | G65: 0.5 | H65: Lot 1 | I65: Devis | J65: Highest
A66: Ahmed Jmal | B66: Back | C66: S01 | D66: US-02-T1 | E66: US-02 – Mot de passe oublié & réinitialisation | F66: Flux reset : génération jeton, envoi e-mail, validation | G66: 1 | H66: Lot 1 | I66: Devis | J66: High
A67: Ahmed Jmal | B67: Back | C67: S01 | D67: US-02-T3 | E67: US-02 – Mot de passe oublié & réinitialisation | F67: Tests automatisés du module d'authentification | G67: 0.5 | H67: Lot 1 | I67: Devis | J67: High
A68: Ahmed Jmal | B68: Back | C68: S01 | D68: US-03-T1 | E68: US-03 – Matrice des rôles et contrôle d'accès | F68: Modèle RBAC : roles, permissions, user_roles | G68: 0.5 | H68: Lot 1 | I68: Devis | J68: Highest
A69: Ahmed Jmal | B69: Back | C69: S01 | D69: US-03-T2 | E69: US-03 – Matrice des rôles et contrôle d'accès | F69: Middleware d'autorisation + cloisonnement par opticien | G69: 1 | H69: Lot 1 | I69: Devis | J69: Highest
A70: Ahmed Jmal | B70: Back | C70: S01 | D70: US-03-T4 | E70: US-03 – Matrice des rôles et contrôle d'accès | F70: Rôles Vendeur et Commercial dans la matrice RBAC | G70: 0.5 | H70: Lot 1 | I70: À valider | J70: Highest
A71: Ahmed Jmal | B71: Back | C71: S01 | D71: US-04-T1 | E71: US-04 – Modèle de données partagé | F71: Conception MCD / MLD et conventions de nommage | G71: 3 | H71: Lot 1 | I71: Devis | J71: Highest
A72: Ahmed Jmal | B72: Back | C72: S01 | D72: US-04-T2 | E72: US-04 – Modèle de données partagé | F72: Dictionnaire de données + matrice de responsabilités | G72: 1 | H72: Lot 1 | I72: Devis | J72: Highest
A73: Ahmed Jmal | B73: Back | C73: S01 | D73: US-04-T3 | E73: US-04 – Modèle de données partagé | F73: Mapping ORM des entités et repositories | G73: 2 | H73: Lot 1 | I73: Devis | J73: Highest
A74: Ahmed Jmal | B74: Back | C74: S02 | D74: US-05-T2 | E74: US-05 – Connexion sécurisée au SI SIVO (Oracle) | F74: Connecteur SIVO + pool de connexions + gestion des erreurs | G74: 2 | H74: Lot 1 | I74: Devis | J74: Highest
A75: Ahmed Jmal | B75: Back | C75: S02 | D75: US-05-T3 | E75: US-05 – Connexion sécurisée au SI SIVO (Oracle) | F75: Synchronisation catalogue / référentiels depuis Oracle SIVO | G75: 2 | H75: Lot 1 | I75: Devis | J75: Highest
... A149: Ahmed Jmal | B149: Back | C149: S12 | D149: US-43-T2 | E149: US-43 – Documentation technique des modules IA | F149: Documentation OpenAPI des services | G149: 0.5 | H149: Lot 3 | I149: Devis | J149: Medium
F150: Sous-total Ahmed Jmal | G150: =SUM(G64:G149) -> 121
A152: Yessine Affes | B152: IA | C152: S06 | D152: US-28-T2 | E152: US-28 – Données et critères de recommandation | F152: Analyse des données + feature engineering | G152: 2.5 | H152: Lot 3 | I152: Devis | J152: High
A153: Yessine Affes | B153: IA | C153: S07 | D153: US-31-T1 | E153: US-31 – Base de connaissances SIVO (RAG) | F153: Pipeline d'ingestion : extraction, chunking, embeddings | G153: 3 | H153: Lot 3 | I153: Devis | J153: High
A154: Yessine Affes | B154: IA | C154: S07 | D154: US-31-T3 | E154: US-31 – Base de connaissances SIVO (RAG) | F154: Retrieval + génération avec citations | G154: 2.5 | H154: Lot 3 | I154: Devis | J154: High
A155: Yessine Affes | B155: IA | C155: S09 | D155: US-29-T1 | E155: US-29 – Moteur de recommandation | F155: Modèle hybride règles métier + ML (ranking) | G155: 4 | H155: Lot 3 | I155: Devis | J155: High
A156: Yessine Affes | B156: IA | C156: S09 | D156: US-29-T2 | E156: US-29 – Moteur de recommandation | F156: Évaluation offline (Recall@k, nDCG) + rapport | G156: 1 | H156: Lot 3 | I156: Devis | J156: High
A157: Yessine Affes | B157: IA | C157: S09 | D157: US-30-T3 | E157: US-30 – Recommandation dans le parcours de commande | F157: Ajustement du modèle à partir des retours de recette | G157: 1.5 | H157: Lot 3 | I157: Devis | J157: Medium
A158: Yessine Affes | B158: IA | C158: S10 | D158: US-32-T1 | E158: US-32 – Suivi de commande conversationnel | F158: Orchestration agent + appels d'outils (statut, détail commande) | G158: 2.5 | H158: Lot 3 | I158: Devis | J158: High
A159: Yessine Affes | B159: IA | C159: S10 | D159: US-32-T3 | E159: US-32 – Suivi de commande conversationnel | F159: Prompt système et garde-fous de réponse | G159: 1.5 | H159: Lot 3 | I159: Devis | J159: High
A160: Yessine Affes | B160: IA | C160: S10 | D160: US-33-T1 | E160: US-33 – Rédaction de réponse formelle | F160: Génération de réponses formelles par gabarits | G160: 2.5 | H160: Lot 3 | I160: Devis | J160: Medium
A161: Yessine Affes | B161: IA | C161: S10 | D161: US-34-T1 | E161: US-34 – Création d'une demande depuis la conversation | F161: Détection d'intention + extraction de champs (structured output) | G161: 2.5 | H161: Lot 3 | I161: Devis | J161: Medium
A162: Yessine Affes | B162: IA | C162: S10 | D162: US-50-T1 | E162: US-50 – FAQ produit, aide à la saisie précal et escalade conseiller | F162: Intentions FAQ / aide précal + règles d'escalade | G162: 2 | H162: Lot 3 | I162: À valider | J162: Medium
A163: Yessine Affes | B163: IA | C163: S11 | D163: US-36-T1 | E163: US-36 – Jeu d'évaluation et évaluation des modules IA | F163: Constitution du golden dataset avec SIVO | G163: 2 | H163: Lot 3 | I163: Devis | J163: High
... A172: Yessine Affes | B172: IA | C172: S12 | D172: US-44-T1 | E172: US-44 – Transfert de connaissances | F172: Atelier de transfert modules IA | G172: 0.5 | H172: Lot 3 | I172: Devis | J172: Medium
F173: Sous-total Yessine Affes | G173: =SUM(G152:G172) -> 40
A175: Heni Kenoun | B175: DevOps | C175: S01 | D175: US-10-T1 | E175: US-10 – Environnements Dev / Recette / Production | F175: Provisionnement infrastructure des 3 environnements | G175: 3 | H175: Lot 1 | I175: Devis | J175: Highest
A176: Heni Kenoun | B176: DevOps | C176: S01 | D176: US-10-T2 | E176: US-10 – Environnements Dev / Recette / Production | F176: Conteneurisation (Docker) front / back / IA | G176: 2 | H176: Lot 1 | I176: Devis | J176: Highest
A177: Heni Kenoun | B177: DevOps | C177: S01 | D177: US-10-T3 | E177: US-10 – Environnements Dev / Recette / Production | F177: Configuration par environnement et gestion des variables | G177: 2 | H177: Lot 1 | I177: Devis | J177: Highest
A178: Heni Kenoun | B178: DevOps | C178: S02 | D178: US-05-T1 | E178: US-05 – Connexion sécurisée au SI SIVO (Oracle) | F178: Comptes de service, droits, ouverture réseau avec IT SIVO | G178: 2 | H178: Lot 1 | I178: Devis | J178: Highest
A179: Heni Kenoun | B179: DevOps | C179: S02 | D179: US-08-T1 | E179: US-08 – Sécuriser les échanges, secrets et données sensibles | F179: TLS + coffre à secrets (Vault / équivalent) par environnement | G179: 1.5 | H179: Lot 1 | I179: Devis | J179: High
A180: Heni Kenoun | B180: DevOps | C180: S02 | D180: US-60-T1 | E180: US-60 – Build et distribution mobile | F180: Pipeline de build mobile + signature des applications | G180: 2 | H180: Lot 1 | I180: À valider | J180: High
A181: Heni Kenoun | B181: DevOps | C181: S02 | D181: US-60-T2 | E181: US-60 – Build et distribution mobile | F181: Distribution TestFlight / Google Play (test interne) | G181: 1 | H181: Lot 1 | I181: À valider | J181: High
A182: Heni Kenoun | B182: DevOps | C182: S03 | D182: US-11-T1 | E182: US-11 – Pipeline CI/CD avec retour arrière | F182: Pipeline build + tests + analyse qualité | G182: 3 | H182: Lot 1 | I182: Devis | J182: High
A183: Heni Kenoun | B183: DevOps | C183: S03 | D183: US-11-T2 | E183: US-11 – Pipeline CI/CD avec retour arrière | F183: Déploiement automatisé + procédure de rollback | G183: 3 | H183: Lot 1 | I183: Devis | J183: High
A184: Heni Kenoun | B184: DevOps | C184: S06 | D184: US-46-T3 | E184: US-46 – Notifications push, e-mail et SMS | F184: Configuration certificats push et fournisseur SMS par environnement | G184: 0.5 | H184: Lot 1 | I184: À valider | J184: High
A185: Heni Kenoun | B185: DevOps | C185: S07 | D185: US-61-T1 | E185: US-61 – Publication sur les stores | F185: Comptes développeur, fiches store, soumission | G185: 1.5 | H185: Lot 1 | I185: À valider | J185: High
A186: Heni Kenoun | B186: DevOps | C186: S09 | D186: US-W00-T3 | E186: US-W00 – Socle front web (réutilise le client API mobile) | F186: Hébergement et déploiement du front web | G186: 1 | H186: Lot 1 | I186: À valider | J186: High
... A196: Heni Kenoun | B196: DevOps | C196: S12 | D196: US-44-T2 | E196: US-44 – Transfert de connaissances | F196: Runbook d'exploitation | G196: 0.5 | H196: Lot 3 | I196: Devis | J196: Medium
F197: Sous-total Heni Kenoun | G197: =SUM(G175:G196) -> 42

Sheet Décisions & DoD
A1: Questions ouvertes à trancher avec SIVO
A2: # | B2: Question | C2: Épic(s) | D2: Bloque le sprint | E2: Propriétaire | F2: Décision
A3: 1 | B3: Avenant : valider les J/H « à valider » (vendeurs, Précal digital, espace commercial, mobile, web, notifications) | C3: Tous | D3: S01 | E3: Direction / commercial
A4: 2 | B4: Échéance février 2027 incompatible avec 1 seul Back : renfort, phasage ou réduction de périmètre ? | C4: Tous | D4: S01 | E4: Direction
A5: 3 | B5: Techno mobile : React Native ou Flutter ? Version minimale iOS / Android ? | C5: E20 | D5: S01 | E5: Équipe tech | F5: Tranché par l'équipe : React Native 0.87 + TypeScript (rapport Front).
A6: 4 | B6: Mode d'authentification : comptes locaux, annuaire SIVO ou SSO ? | C6: E01 | D6: S01 | E6: IT SIVO | F6: De fait : comptes locaux e-mail / mot de passe + JWT (OPT-102). SSO à confirmer avec SIVO.
A7: 5 | B7: Accès Oracle SIVO : mode d'intégration (API, vues, base partagée), propriétaires des tables | C7: E03 | D7: S01 | E7: IT SIVO
A8: 6 | B8: Hébergement (cloud / on-premise SIVO) et règles de mise en production | C8: E05 | D8: S01 | E8: IT SIVO
A9: 7 | B9: Vendeurs : permissions disponibles (commander, voir prix, réclamer…) ; plages horaires par vendeur ou par site ? | C9: E18 | D9: S02 | E9: SIVO métier | F9: Partiel : plages par affectation vendeur ↔ site (OPT-203). Permissions encore à définir.
A10: 8 | B10: Vendeurs : l'opticien peut-il avoir plusieurs sites dans des fuseaux différents ? | C10: E18 | D10: S03 | E10: SIVO métier | F10: Oui : fuseau IANA par site (OPT-203).
A11: 9 | B11: Format des fichiers traceur à importer pour le calibre précal (OMA / VCA ?) | C11: E09 | D11: S05 | E11: SIVO technique
A12: 10 | B12: Plages autorisées et champs obligatoires par type de verre (précal et RX) | C12: E06, E09 | D12: S04 | E12: SIVO produit
A13: 11 | B13: Statuts clés déclenchant push / e-mail / SMS ; fournisseur SMS | C13: E07 | D13: S06 | E13: SIVO métier
A14: 12 | B14: Workflow réclamation : délais (SLA), règles de décision reprise / échange / avoir | C14: E13 | D14: S06 | E14: SIVO métier
A15: 13 | B15: Espace commercial : source de l'affectation représentant ↔ clients | C15: E19 | D15: S08 | E15: SIVO commercial
A16: 14 | B16: Critères de recommandation et seuil Recall@3 accepté | C16: E10 | D16: S09 | E16: SIVO produit
A17: 15 | B17: Sources documentaires autorisées pour le chatbot ; canal d'escalade conseiller | C17: E11 | D17: S07 | E17: SIVO
A18: 16 | B18: Volumétrie cible, RTO / RPO et outils de supervision imposés | C18: E14, E15 | D18: S11 | E18: IT SIVO
A20: Definition of Ready (story)
B21: ☐ User story « En tant que… je veux… afin de… »
B22: ☐ Critères d'acceptation testables
B23: ☐ Questions bloquantes levées (tableau ci-dessus)
B24: ☐ Maquette mobile disponible (et web pour les stories web)
B25: ☐ Accès données / API Oracle disponibles
B26: ☐ Sous-tâches Front Mobile / Front Web / Back / IA / DevOps estimées ≤ 3 J/H
A28: Definition of Done
B29: ☐ Code revu et mergé ; tests unitaires + intégration verts dans la CI
B30: ☐ Critères d'acceptation vérifiés par le PO sur appareil réel (iOS ET Android)
B31: ☐ Migrations BDD versionnées et rejouables
B32: ☐ Aucune faille critique (scan sécurité / secrets)
B33: ☐ Documentation API mise à jour
B34: ☐ IA : métriques mesurées vs seuils, fallback testé, version du modèle tracée
B35: ☐ Déployé en Recette via le pipeline (build mobile distribué)

Sheet Changements v2
A1: Ce qui a changé par rapport à la v1
A2: • Nouvel épic E18 — Module vendeurs & gestion des accès (Lot 1) : compte opticien et sites, vendeurs, rattachement aux sites, plages jours/heures, permissions.
A3: • Nouvel épic E19 — Espace commercial (Lot 2, CDC §3.9).
A4: • Nouvel épic E20 — Socle application mobile iOS/Android + publication stores ; stories « Version web » ajoutées à chaque épic.
A5: • E09 Précal : devient le bon précal digital complet (CDC §3.2) et passe en Lot 1 ; la détection IA des bons papier est retirée.
A6: • E13 Réclamations : passe du Lot 2 au Lot 1 (CDC v2) ; motifs et workflow alignés (diagnostic → reprise / échange / avoir → clôture).
A7: • E06 : sélection guidée monture + options ; E07 : notifications push / e-mail / SMS ; E08 : modification / réordonnancement ; E12 : code ou photo de réception ; E11 : FAQ, aide précal, escalade.
A8: • Rôles : la BDD est confiée au Back ; le rôle restant devient DevOps seul ; Front scindé en Front Mobile (d'abord) et Front Web (ensuite).
A9: • Colonne « Source charge » : Devis (couvert par le devis signé) ou À valider (avenant).
A10: • 12 sprints (au lieu de 10), contrôle automatique de l'échéance février 2027.

Sheet Import Jira
A1: Importer le backlog dans Jira (Jira_Import_SIVO_v3.csv)
A2: 1. Projet Scrum (company-managed). Créer les versions « Lot 1 », « Lot 2 », « Lot 3 » et les composants Front Mobile, Front Web, Back, IA, DevOps.
A3: 2. Créer les sprints S01…S12 dans le board avant l'import (sinon ignorer la colonne Sprint et filtrer par label S01…S12).
A4: 3. Paramètres système > Importation externe > CSV, encodage UTF-8, séparateur virgule.
A5: 4. Mapping : Issue Id → Issue ID ; Assignee → Responsable (les utilisateurs doivent exister dans Jira — à l'étape « mapping des valeurs », associer chaque nom à son compte) ; Parent Id → Parent ; Issue Type ; Summary ; Description ; Priority ; Labels (4 colonnes) → Étiquettes ; Component → Composants ;
A6: Fix Version → Versions corrigées ; Sprint ; Story Points → Story point estimate ; Original Estimate (secondes, 1 J/H = 28 800 s) ; Epic Name.
A7: 5. Types requis : Epic, Story, Sub-task (en français : mapper Sub-task → Sous-tâche).
A8: 6. Affectation déjà incluse (colonne Assignee). Story = assignée au développeur qui porte la plus grande part ; sous-tâches = développeur du rôle. Label « a-valider » = charge hors devis.
A9: ⚠ Si la v1 a déjà été importée : supprimer ou archiver les tickets v1 avant (les clés US-20, US-21 ont changé de contenu).
